[
  {
    "id": "kh-iy-sure-0001",
    "lessonId": "idari_yargilama_hukuku",
    "topicId": "idari_yargida_sureler_kanun_yollari",
    "question": "Özel kanunda ayrı süre bulunmayan bir idari işleme karşı idare mahkemesinde dava açılacaktır. Genel süre nedir?",
    "choices": {
      "C": "Altmış gün",
      "A": "Çalışmaya ara verme bütün idari dava sürelerini ara verme boyunca durdurur ve kalan süre sonradan aynen işletilir",
      "B": "İdari makama yapılan her başvuru, kanuni süresi dışında yapılsa bile sona ermiş dava açma süresini yeniden başlatır",
      "D": "Yazılı bildirim bulunması hâlinde süre bildirimi izleyen gün değil, işlemin idarece hazırlandığı tarihte başlar",
      "E": "Görevsiz adli yargı yerine yapılan başvurunun tarihi hiçbir koşulda korunmaz ve dava daima süreden reddedilir"
    },
    "correctAnswer": "C",
    "explanation": "Özel kanunda ayrı süre yoksa Danıştay ve idare mahkemelerinde dava açma süresi altmış gündür.",
    "source": {
      "kind": "generated",
      "styleRef": "2026 SMMM beş seçenekli test",
      "legislationRef": "2577 sayılı İYUK m.7/1"
    },
    "tags": [
      "Demo Soru",
      "2026 Formatı",
      "Konu Havuzu",
      "Süreler ve Kanun Yolları"
    ],
    "difficulty": "easy",
    "updatedAt": "2026-07-16T00:00:00Z",
    "examPeriod": "2026 test sistemine uyumlu özgün soru",
    "legislationVersion": "2577 sayılı İYUK (16.07.2026)",
    "sourceUpdatedAt": "2026-07-16T00:00:00Z",
    "isPremium": false,
    "isActive": true
  },
  {
    "id": "kh-iy-sure-0002",
    "lessonId": "idari_yargilama_hukuku",
    "topicId": "idari_yargida_sureler_kanun_yollari",
    "question": "Danıştay ve idare mahkemelerinde genel dava açma süresi kaç gündür?",
    "choices": {
      "D": "Altmış gün",
      "A": "Çalışmaya ara verme bütün idari dava sürelerini ara verme boyunca durdurur ve kalan süre sonradan aynen işletilir",
      "B": "İdari makama yapılan her başvuru, kanuni süresi dışında yapılsa bile sona ermiş dava açma süresini yeniden başlatır",
      "C": "Yazılı bildirim bulunması hâlinde süre bildirimi izleyen gün değil, işlemin idarece hazırlandığı tarihte başlar",
      "E": "Görevsiz adli yargı yerine yapılan başvurunun tarihi hiçbir koşulda korunmaz ve dava daima süreden reddedilir"
    },
    "correctAnswer": "D",
    "explanation": "Özel kanunda ayrı süre yoksa Danıştay ve idare mahkemelerinde dava açma süresi altmış gündür.",
    "source": {
      "kind": "generated",
      "styleRef": "2026 SMMM beş seçenekli test",
      "legislationRef": "2577 sayılı İYUK m.7/1"
    },
    "tags": [
      "Demo Soru",
      "2026 Formatı",
      "Konu Havuzu",
      "Süreler ve Kanun Yolları"
    ],
    "difficulty": "easy",
    "updatedAt": "2026-07-16T00:00:00Z",
    "examPeriod": "2026 test sistemine uyumlu özgün soru",
    "legislationVersion": "2577 sayılı İYUK (16.07.2026)",
    "sourceUpdatedAt": "2026-07-16T00:00:00Z",
    "isPremium": false,
    "isActive": true
  },
  {
    "id": "kh-iy-sure-0003",
    "lessonId": "idari_yargilama_hukuku",
    "topicId": "idari_yargida_sureler_kanun_yollari",
    "question": "Özel kanunda ayrı süre bulunmayan vergi tarhiyatına karşı vergi mahkemesinde dava açılacaktır. Genel süre nedir?",
    "choices": {
      "D": "Otuz gün",
      "A": "Görevsiz adli yargı yerine yapılan başvurunun tarihi hiçbir koşulda korunmaz ve dava daima süreden reddedilir",
      "B": "Kanunda günle belirlenen sürelerin hesabında resmî tatiller tamamen dışarıda bırakılarak yalnız mesai günleri sayılır",
      "C": "Süre bildirimin yapıldığı gün başlar ve hafta sonları hesaba katılmadan yalnız iş günleri üzerinden yürür",
      "E": "Özel kanunda farklı süre olsa bile bütün idari davalarda değişmez biçimde doksan günlük tek süre uygulanır"
    },
    "correctAnswer": "D",
    "explanation": "Vergi mahkemelerinde özel kanunda ayrı süre yoksa genel dava açma süresi otuz gündür.",
    "source": {
      "kind": "generated",
      "styleRef": "2026 SMMM beş seçenekli test",
      "legislationRef": "2577 sayılı İYUK m.7/1"
    },
    "tags": [
      "Demo Soru",
      "2026 Formatı",
      "Konu Havuzu",
      "Süreler ve Kanun Yolları"
    ],
    "difficulty": "easy",
    "updatedAt": "2026-07-16T00:00:00Z",
    "examPeriod": "2026 test sistemine uyumlu özgün soru",
    "legislationVersion": "2577 sayılı İYUK (16.07.2026)",
    "sourceUpdatedAt": "2026-07-16T00:00:00Z",
    "isPremium": false,
    "isActive": true
  },
  {
    "id": "kh-iy-sure-0004",
    "lessonId": "idari_yargilama_hukuku",
    "topicId": "idari_yargida_sureler_kanun_yollari",
    "question": "Vergi mahkemelerinde genel dava açma süresi kaç gündür?",
    "choices": {
      "B": "Otuz gün",
      "A": "Görevsiz adli yargı yerine yapılan başvurunun tarihi hiçbir koşulda korunmaz ve dava daima süreden reddedilir",
      "C": "Kanunda günle belirlenen sürelerin hesabında resmî tatiller tamamen dışarıda bırakılarak yalnız mesai günleri sayılır",
      "D": "Süre bildirimin yapıldığı gün başlar ve hafta sonları hesaba katılmadan yalnız iş günleri üzerinden yürür",
      "E": "Özel kanunda farklı süre olsa bile bütün idari davalarda değişmez biçimde doksan günlük tek süre uygulanır"
    },
    "correctAnswer": "B",
    "explanation": "Vergi mahkemelerinde özel kanunda ayrı süre yoksa genel dava açma süresi otuz gündür.",
    "source": {
      "kind": "generated",
      "styleRef": "2026 SMMM beş seçenekli test",
      "legislationRef": "2577 sayılı İYUK m.7/1"
    },
    "tags": [
      "Demo Soru",
      "2026 Formatı",
      "Konu Havuzu",
      "Süreler ve Kanun Yolları"
    ],
    "difficulty": "easy",
    "updatedAt": "2026-07-16T00:00:00Z",
    "examPeriod": "2026 test sistemine uyumlu özgün soru",
    "legislationVersion": "2577 sayılı İYUK (16.07.2026)",
    "sourceUpdatedAt": "2026-07-16T00:00:00Z",
    "isPremium": false,
    "isActive": true
  },
  {
    "id": "kh-iy-sure-0005",
    "lessonId": "idari_yargilama_hukuku",
    "topicId": "idari_yargida_sureler_kanun_yollari",
    "question": "İdari işlem 4 Ağustos günü usulüne uygun yazılı olarak bildirilmiştir. Dava süresi hangi gün işlemeye başlar?",
    "choices": {
      "D": "Bildirimi izleyen gün",
      "A": "Özel kanunda farklı süre olsa bile bütün idari davalarda değişmez biçimde doksan günlük tek süre uygulanır",
      "B": "Sürenin son günü tatile rastlarsa önceki çalışma gününde sona erer ve sonraki güne uzaması mümkün değildir",
      "C": "Çalışmaya ara verme bütün idari dava sürelerini ara verme boyunca durdurur ve kalan süre sonradan aynen işletilir",
      "E": "İdari makama yapılan her başvuru, kanuni süresi dışında yapılsa bile sona ermiş dava açma süresini yeniden başlatır"
    },
    "correctAnswer": "D",
    "explanation": "İdari süreler tebliğ, yayın veya ilan tarihini izleyen günden itibaren işlemeye başlar.",
    "source": {
      "kind": "generated",
      "styleRef": "2026 SMMM beş seçenekli test",
      "legislationRef": "2577 sayılı İYUK m.7/2, m.8/1"
    },
    "tags": [
      "Demo Soru",
      "2026 Formatı",
      "Konu Havuzu",
      "Süreler ve Kanun Yolları"
    ],
    "difficulty": "medium",
    "updatedAt": "2026-07-16T00:00:00Z",
    "examPeriod": "2026 test sistemine uyumlu özgün soru",
    "legislationVersion": "2577 sayılı İYUK (16.07.2026)",
    "sourceUpdatedAt": "2026-07-16T00:00:00Z",
    "isPremium": false,
    "isActive": true
  },
  {
    "id": "kh-iy-sure-0006",
    "lessonId": "idari_yargilama_hukuku",
    "topicId": "idari_yargida_sureler_kanun_yollari",
    "question": "Yazılı bildirimde dava süresinin başlangıcına ilişkin genel kural hangisidir?",
    "choices": {
      "B": "Bildirimi izleyen gün",
      "A": "Özel kanunda farklı süre olsa bile bütün idari davalarda değişmez biçimde doksan günlük tek süre uygulanır",
      "C": "Sürenin son günü tatile rastlarsa önceki çalışma gününde sona erer ve sonraki güne uzaması mümkün değildir",
      "D": "Çalışmaya ara verme bütün idari dava sürelerini ara verme boyunca durdurur ve kalan süre sonradan aynen işletilir",
      "E": "İdari makama yapılan her başvuru, kanuni süresi dışında yapılsa bile sona ermiş dava açma süresini yeniden başlatır"
    },
    "correctAnswer": "B",
    "explanation": "İdari süreler tebliğ, yayın veya ilan tarihini izleyen günden itibaren işlemeye başlar.",
    "source": {
      "kind": "generated",
      "styleRef": "2026 SMMM beş seçenekli test",
      "legislationRef": "2577 sayılı İYUK m.7/2, m.8/1"
    },
    "tags": [
      "Demo Soru",
      "2026 Formatı",
      "Konu Havuzu",
      "Süreler ve Kanun Yolları"
    ],
    "difficulty": "medium",
    "updatedAt": "2026-07-16T00:00:00Z",
    "examPeriod": "2026 test sistemine uyumlu özgün soru",
    "legislationVersion": "2577 sayılı İYUK (16.07.2026)",
    "sourceUpdatedAt": "2026-07-16T00:00:00Z",
    "isPremium": false,
    "isActive": true
  },
  {
    "id": "kh-iy-sure-0007",
    "lessonId": "idari_yargilama_hukuku",
    "topicId": "idari_yargida_sureler_kanun_yollari",
    "question": "Adresi bilinmeyen kişiye özel kanuna uygun ilanla bildirim yapılmış ve özel kanunda aksi düzenlenmemiştir. Süre nasıl başlar?",
    "choices": {
      "B": "Son ilanı izleyen günden on beş gün sonra",
      "A": "İdari makama yapılan her başvuru, kanuni süresi dışında yapılsa bile sona ermiş dava açma süresini yeniden başlatır",
      "C": "Yazılı bildirim bulunması hâlinde süre bildirimi izleyen gün değil, işlemin idarece hazırlandığı tarihte başlar",
      "D": "Görevsiz adli yargı yerine yapılan başvurunun tarihi hiçbir koşulda korunmaz ve dava daima süreden reddedilir",
      "E": "Kanunda günle belirlenen sürelerin hesabında resmî tatiller tamamen dışarıda bırakılarak yalnız mesai günleri sayılır"
    },
    "correctAnswer": "B",
    "explanation": "Özel kanunda aksi yoksa ilanla bildirimde dava süresi son ilan tarihini izleyen günden on beş gün sonra işlemeye başlar.",
    "source": {
      "kind": "generated",
      "styleRef": "2026 SMMM beş seçenekli test",
      "legislationRef": "2577 sayılı İYUK m.7/3"
    },
    "tags": [
      "Demo Soru",
      "2026 Formatı",
      "Konu Havuzu",
      "Süreler ve Kanun Yolları"
    ],
    "difficulty": "hard",
    "updatedAt": "2026-07-16T00:00:00Z",
    "examPeriod": "2026 test sistemine uyumlu özgün soru",
    "legislationVersion": "2577 sayılı İYUK (16.07.2026)",
    "sourceUpdatedAt": "2026-07-16T00:00:00Z",
    "isPremium": false,
    "isActive": true
  },
  {
    "id": "kh-iy-sure-0008",
    "lessonId": "idari_yargilama_hukuku",
    "topicId": "idari_yargida_sureler_kanun_yollari",
    "question": "İlan yoluyla bildirimde son ilandan sonra uygulanan yapısal bekleme süresi nedir?",
    "choices": {
      "E": "Son ilanı izleyen günden on beş gün sonra",
      "A": "İdari makama yapılan her başvuru, kanuni süresi dışında yapılsa bile sona ermiş dava açma süresini yeniden başlatır",
      "B": "Yazılı bildirim bulunması hâlinde süre bildirimi izleyen gün değil, işlemin idarece hazırlandığı tarihte başlar",
      "C": "Görevsiz adli yargı yerine yapılan başvurunun tarihi hiçbir koşulda korunmaz ve dava daima süreden reddedilir",
      "D": "Kanunda günle belirlenen sürelerin hesabında resmî tatiller tamamen dışarıda bırakılarak yalnız mesai günleri sayılır"
    },
    "correctAnswer": "E",
    "explanation": "Özel kanunda aksi yoksa ilanla bildirimde dava süresi son ilan tarihini izleyen günden on beş gün sonra işlemeye başlar.",
    "source": {
      "kind": "generated",
      "styleRef": "2026 SMMM beş seçenekli test",
      "legislationRef": "2577 sayılı İYUK m.7/3"
    },
    "tags": [
      "Demo Soru",
      "2026 Formatı",
      "Konu Havuzu",
      "Süreler ve Kanun Yolları"
    ],
    "difficulty": "hard",
    "updatedAt": "2026-07-16T00:00:00Z",
    "examPeriod": "2026 test sistemine uyumlu özgün soru",
    "legislationVersion": "2577 sayılı İYUK (16.07.2026)",
    "sourceUpdatedAt": "2026-07-16T00:00:00Z",
    "isPremium": false,
    "isActive": true
  },
  {
    "id": "kh-iy-sure-0009",
    "lessonId": "idari_yargilama_hukuku",
    "topicId": "idari_yargida_sureler_kanun_yollari",
    "question": "İlanı gereken düzenleyici işlem Resmî Gazete'de yayımlanmıştır. Dava süresi hangi tarihten başlar?",
    "choices": {
      "C": "İlan tarihini izleyen gün",
      "A": "Kanunda günle belirlenen sürelerin hesabında resmî tatiller tamamen dışarıda bırakılarak yalnız mesai günleri sayılır",
      "B": "Süre bildirimin yapıldığı gün başlar ve hafta sonları hesaba katılmadan yalnız iş günleri üzerinden yürür",
      "D": "Özel kanunda farklı süre olsa bile bütün idari davalarda değişmez biçimde doksan günlük tek süre uygulanır",
      "E": "Sürenin son günü tatile rastlarsa önceki çalışma gününde sona erer ve sonraki güne uzaması mümkün değildir"
    },
    "correctAnswer": "C",
    "explanation": "Düzenleyici işlemlerde dava süresi ilan tarihini izleyen günden itibaren başlar.",
    "source": {
      "kind": "generated",
      "styleRef": "2026 SMMM beş seçenekli test",
      "legislationRef": "2577 sayılı İYUK m.7/4"
    },
    "tags": [
      "Demo Soru",
      "2026 Formatı",
      "Konu Havuzu",
      "Süreler ve Kanun Yolları"
    ],
    "difficulty": "medium",
    "updatedAt": "2026-07-16T00:00:00Z",
    "examPeriod": "2026 test sistemine uyumlu özgün soru",
    "legislationVersion": "2577 sayılı İYUK (16.07.2026)",
    "sourceUpdatedAt": "2026-07-16T00:00:00Z",
    "isPremium": false,
    "isActive": true
  },
  {
    "id": "kh-iy-sure-0010",
    "lessonId": "idari_yargilama_hukuku",
    "topicId": "idari_yargida_sureler_kanun_yollari",
    "question": "İlanı gereken düzenleyici işlemlerde dava süresinin başlangıcı hangisidir?",
    "choices": {
      "A": "İlan tarihini izleyen gün",
      "B": "Kanunda günle belirlenen sürelerin hesabında resmî tatiller tamamen dışarıda bırakılarak yalnız mesai günleri sayılır",
      "C": "Süre bildirimin yapıldığı gün başlar ve hafta sonları hesaba katılmadan yalnız iş günleri üzerinden yürür",
      "D": "Özel kanunda farklı süre olsa bile bütün idari davalarda değişmez biçimde doksan günlük tek süre uygulanır",
      "E": "Sürenin son günü tatile rastlarsa önceki çalışma gününde sona erer ve sonraki güne uzaması mümkün değildir"
    },
    "correctAnswer": "A",
    "explanation": "Düzenleyici işlemlerde dava süresi ilan tarihini izleyen günden itibaren başlar.",
    "source": {
      "kind": "generated",
      "styleRef": "2026 SMMM beş seçenekli test",
      "legislationRef": "2577 sayılı İYUK m.7/4"
    },
    "tags": [
      "Demo Soru",
      "2026 Formatı",
      "Konu Havuzu",
      "Süreler ve Kanun Yolları"
    ],
    "difficulty": "medium",
    "updatedAt": "2026-07-16T00:00:00Z",
    "examPeriod": "2026 test sistemine uyumlu özgün soru",
    "legislationVersion": "2577 sayılı İYUK (16.07.2026)",
    "sourceUpdatedAt": "2026-07-16T00:00:00Z",
    "isPremium": false,
    "isActive": true
  },
  {
    "id": "kh-iy-sure-0011",
    "lessonId": "idari_yargilama_hukuku",
    "topicId": "idari_yargida_sureler_kanun_yollari",
    "question": "Dava açma süresinin ortasındaki resmî tatiller hesaplama bakımından nasıl değerlendirilir?",
    "choices": {
      "D": "Tatil günleri süreye dâhildir",
      "A": "Sürenin son günü tatile rastlarsa önceki çalışma gününde sona erer ve sonraki güne uzaması mümkün değildir",
      "B": "Çalışmaya ara verme bütün idari dava sürelerini ara verme boyunca durdurur ve kalan süre sonradan aynen işletilir",
      "C": "İdari makama yapılan her başvuru, kanuni süresi dışında yapılsa bile sona ermiş dava açma süresini yeniden başlatır",
      "E": "Yazılı bildirim bulunması hâlinde süre bildirimi izleyen gün değil, işlemin idarece hazırlandığı tarihte başlar"
    },
    "correctAnswer": "D",
    "explanation": "Tatil günleri süre hesabına dâhildir; yalnız son gün tatile rastlarsa uzama olur.",
    "source": {
      "kind": "generated",
      "styleRef": "2026 SMMM beş seçenekli test",
      "legislationRef": "2577 sayılı İYUK m.8/2"
    },
    "tags": [
      "Demo Soru",
      "2026 Formatı",
      "Konu Havuzu",
      "Süreler ve Kanun Yolları"
    ],
    "difficulty": "easy",
    "updatedAt": "2026-07-16T00:00:00Z",
    "examPeriod": "2026 test sistemine uyumlu özgün soru",
    "legislationVersion": "2577 sayılı İYUK (16.07.2026)",
    "sourceUpdatedAt": "2026-07-16T00:00:00Z",
    "isPremium": false,
    "isActive": true
  },
  {
    "id": "kh-iy-sure-0012",
    "lessonId": "idari_yargilama_hukuku",
    "topicId": "idari_yargida_sureler_kanun_yollari",
    "question": "İYUK'a göre tatil günlerinin sürelere etkisi hangisidir?",
    "choices": {
      "C": "Tatil günleri süreye dâhildir",
      "A": "Sürenin son günü tatile rastlarsa önceki çalışma gününde sona erer ve sonraki güne uzaması mümkün değildir",
      "B": "Çalışmaya ara verme bütün idari dava sürelerini ara verme boyunca durdurur ve kalan süre sonradan aynen işletilir",
      "D": "İdari makama yapılan her başvuru, kanuni süresi dışında yapılsa bile sona ermiş dava açma süresini yeniden başlatır",
      "E": "Yazılı bildirim bulunması hâlinde süre bildirimi izleyen gün değil, işlemin idarece hazırlandığı tarihte başlar"
    },
    "correctAnswer": "C",
    "explanation": "Tatil günleri süre hesabına dâhildir; yalnız son gün tatile rastlarsa uzama olur.",
    "source": {
      "kind": "generated",
      "styleRef": "2026 SMMM beş seçenekli test",
      "legislationRef": "2577 sayılı İYUK m.8/2"
    },
    "tags": [
      "Demo Soru",
      "2026 Formatı",
      "Konu Havuzu",
      "Süreler ve Kanun Yolları"
    ],
    "difficulty": "easy",
    "updatedAt": "2026-07-16T00:00:00Z",
    "examPeriod": "2026 test sistemine uyumlu özgün soru",
    "legislationVersion": "2577 sayılı İYUK (16.07.2026)",
    "sourceUpdatedAt": "2026-07-16T00:00:00Z",
    "isPremium": false,
    "isActive": true
  },
  {
    "id": "kh-iy-sure-0013",
    "lessonId": "idari_yargilama_hukuku",
    "topicId": "idari_yargida_sureler_kanun_yollari",
    "question": "Kanuni sürenin son günü pazar gününe rastlamıştır. Süre ne zaman sona erer?",
    "choices": {
      "E": "İzleyen çalışma gününün sonunda",
      "A": "Yazılı bildirim bulunması hâlinde süre bildirimi izleyen gün değil, işlemin idarece hazırlandığı tarihte başlar",
      "B": "Görevsiz adli yargı yerine yapılan başvurunun tarihi hiçbir koşulda korunmaz ve dava daima süreden reddedilir",
      "C": "Kanunda günle belirlenen sürelerin hesabında resmî tatiller tamamen dışarıda bırakılarak yalnız mesai günleri sayılır",
      "D": "Süre bildirimin yapıldığı gün başlar ve hafta sonları hesaba katılmadan yalnız iş günleri üzerinden yürür"
    },
    "correctAnswer": "E",
    "explanation": "Son gün tatilse süre tatili izleyen çalışma gününün bitimine kadar uzar.",
    "source": {
      "kind": "generated",
      "styleRef": "2026 SMMM beş seçenekli test",
      "legislationRef": "2577 sayılı İYUK m.8/2"
    },
    "tags": [
      "Demo Soru",
      "2026 Formatı",
      "Konu Havuzu",
      "Süreler ve Kanun Yolları"
    ],
    "difficulty": "medium",
    "updatedAt": "2026-07-16T00:00:00Z",
    "examPeriod": "2026 test sistemine uyumlu özgün soru",
    "legislationVersion": "2577 sayılı İYUK (16.07.2026)",
    "sourceUpdatedAt": "2026-07-16T00:00:00Z",
    "isPremium": false,
    "isActive": true
  },
  {
    "id": "kh-iy-sure-0014",
    "lessonId": "idari_yargilama_hukuku",
    "topicId": "idari_yargida_sureler_kanun_yollari",
    "question": "Sürenin son gününün tatil olması hâlindeki uzama kuralı hangisidir?",
    "choices": {
      "A": "İzleyen çalışma gününün sonunda",
      "B": "Yazılı bildirim bulunması hâlinde süre bildirimi izleyen gün değil, işlemin idarece hazırlandığı tarihte başlar",
      "C": "Görevsiz adli yargı yerine yapılan başvurunun tarihi hiçbir koşulda korunmaz ve dava daima süreden reddedilir",
      "D": "Kanunda günle belirlenen sürelerin hesabında resmî tatiller tamamen dışarıda bırakılarak yalnız mesai günleri sayılır",
      "E": "Süre bildirimin yapıldığı gün başlar ve hafta sonları hesaba katılmadan yalnız iş günleri üzerinden yürür"
    },
    "correctAnswer": "A",
    "explanation": "Son gün tatilse süre tatili izleyen çalışma gününün bitimine kadar uzar.",
    "source": {
      "kind": "generated",
      "styleRef": "2026 SMMM beş seçenekli test",
      "legislationRef": "2577 sayılı İYUK m.8/2"
    },
    "tags": [
      "Demo Soru",
      "2026 Formatı",
      "Konu Havuzu",
      "Süreler ve Kanun Yolları"
    ],
    "difficulty": "medium",
    "updatedAt": "2026-07-16T00:00:00Z",
    "examPeriod": "2026 test sistemine uyumlu özgün soru",
    "legislationVersion": "2577 sayılı İYUK (16.07.2026)",
    "sourceUpdatedAt": "2026-07-16T00:00:00Z",
    "isPremium": false,
    "isActive": true
  },
  {
    "id": "kh-iy-sure-0015",
    "lessonId": "idari_yargilama_hukuku",
    "topicId": "idari_yargida_sureler_kanun_yollari",
    "question": "İYUK'ta yazılı bir sürenin bitişi mahkemelerin çalışmaya ara verme zamanına rastlamıştır. Kanuni sonuç nedir?",
    "choices": {
      "E": "Ara vermenin bitimini izleyen tarihten yedi gün",
      "A": "Süre bildirimin yapıldığı gün başlar ve hafta sonları hesaba katılmadan yalnız iş günleri üzerinden yürür",
      "B": "Özel kanunda farklı süre olsa bile bütün idari davalarda değişmez biçimde doksan günlük tek süre uygulanır",
      "C": "Sürenin son günü tatile rastlarsa önceki çalışma gününde sona erer ve sonraki güne uzaması mümkün değildir",
      "D": "Çalışmaya ara verme bütün idari dava sürelerini ara verme boyunca durdurur ve kalan süre sonradan aynen işletilir"
    },
    "correctAnswer": "E",
    "explanation": "İYUK'ta yazılı süre, çalışmaya ara vermenin sona erdiği günü izleyen tarihten itibaren yedi gün uzamış sayılır.",
    "source": {
      "kind": "generated",
      "styleRef": "2026 SMMM beş seçenekli test",
      "legislationRef": "2577 sayılı İYUK m.8/3"
    },
    "tags": [
      "Demo Soru",
      "2026 Formatı",
      "Konu Havuzu",
      "Süreler ve Kanun Yolları"
    ],
    "difficulty": "hard",
    "updatedAt": "2026-07-16T00:00:00Z",
    "examPeriod": "2026 test sistemine uyumlu özgün soru",
    "legislationVersion": "2577 sayılı İYUK (16.07.2026)",
    "sourceUpdatedAt": "2026-07-16T00:00:00Z",
    "isPremium": false,
    "isActive": true
  },
  {
    "id": "kh-iy-sure-0016",
    "lessonId": "idari_yargilama_hukuku",
    "topicId": "idari_yargida_sureler_kanun_yollari",
    "question": "Çalışmaya ara vermeye rastlayan İYUK süreleri ne kadar uzamış sayılır?",
    "choices": {
      "E": "Ara vermenin bitimini izleyen tarihten yedi gün",
      "A": "Süre bildirimin yapıldığı gün başlar ve hafta sonları hesaba katılmadan yalnız iş günleri üzerinden yürür",
      "B": "Özel kanunda farklı süre olsa bile bütün idari davalarda değişmez biçimde doksan günlük tek süre uygulanır",
      "C": "Sürenin son günü tatile rastlarsa önceki çalışma gününde sona erer ve sonraki güne uzaması mümkün değildir",
      "D": "Çalışmaya ara verme bütün idari dava sürelerini ara verme boyunca durdurur ve kalan süre sonradan aynen işletilir"
    },
    "correctAnswer": "E",
    "explanation": "İYUK'ta yazılı süre, çalışmaya ara vermenin sona erdiği günü izleyen tarihten itibaren yedi gün uzamış sayılır.",
    "source": {
      "kind": "generated",
      "styleRef": "2026 SMMM beş seçenekli test",
      "legislationRef": "2577 sayılı İYUK m.8/3"
    },
    "tags": [
      "Demo Soru",
      "2026 Formatı",
      "Konu Havuzu",
      "Süreler ve Kanun Yolları"
    ],
    "difficulty": "hard",
    "updatedAt": "2026-07-16T00:00:00Z",
    "examPeriod": "2026 test sistemine uyumlu özgün soru",
    "legislationVersion": "2577 sayılı İYUK (16.07.2026)",
    "sourceUpdatedAt": "2026-07-16T00:00:00Z",
    "isPremium": false,
    "isActive": true
  },
  {
    "id": "kh-iy-sure-0017",
    "lessonId": "idari_yargilama_hukuku",
    "topicId": "idari_yargida_sureler_kanun_yollari",
    "question": "Adli yargıdaki dava görev yönünden reddedilmiş ve karar kesinleşmiştir. İdari yargıda başvuru için tanınan yapısal süre nedir?",
    "choices": {
      "A": "Otuz gün",
      "B": "Çalışmaya ara verme bütün idari dava sürelerini ara verme boyunca durdurur ve kalan süre sonradan aynen işletilir",
      "C": "İdari makama yapılan her başvuru, kanuni süresi dışında yapılsa bile sona ermiş dava açma süresini yeniden başlatır",
      "D": "Yazılı bildirim bulunması hâlinde süre bildirimi izleyen gün değil, işlemin idarece hazırlandığı tarihte başlar",
      "E": "Görevsiz adli yargı yerine yapılan başvurunun tarihi hiçbir koşulda korunmaz ve dava daima süreden reddedilir"
    },
    "correctAnswer": "A",
    "explanation": "Görevsizlik kararının kesinleşmesini izleyen günden itibaren otuz gün içinde görevli idari yargı yerinde dava açılabilir.",
    "source": {
      "kind": "generated",
      "styleRef": "2026 SMMM beş seçenekli test",
      "legislationRef": "2577 sayılı İYUK m.9"
    },
    "tags": [
      "Demo Soru",
      "2026 Formatı",
      "Konu Havuzu",
      "Süreler ve Kanun Yolları"
    ],
    "difficulty": "medium",
    "updatedAt": "2026-07-16T00:00:00Z",
    "examPeriod": "2026 test sistemine uyumlu özgün soru",
    "legislationVersion": "2577 sayılı İYUK (16.07.2026)",
    "sourceUpdatedAt": "2026-07-16T00:00:00Z",
    "isPremium": false,
    "isActive": true
  },
  {
    "id": "kh-iy-sure-0018",
    "lessonId": "idari_yargilama_hukuku",
    "topicId": "idari_yargida_sureler_kanun_yollari",
    "question": "Görevsiz adli yargı kararının kesinleşmesinden sonra idari dava açma süresi kaç gündür?",
    "choices": {
      "E": "Otuz gün",
      "A": "Çalışmaya ara verme bütün idari dava sürelerini ara verme boyunca durdurur ve kalan süre sonradan aynen işletilir",
      "B": "İdari makama yapılan her başvuru, kanuni süresi dışında yapılsa bile sona ermiş dava açma süresini yeniden başlatır",
      "C": "Yazılı bildirim bulunması hâlinde süre bildirimi izleyen gün değil, işlemin idarece hazırlandığı tarihte başlar",
      "D": "Görevsiz adli yargı yerine yapılan başvurunun tarihi hiçbir koşulda korunmaz ve dava daima süreden reddedilir"
    },
    "correctAnswer": "E",
    "explanation": "Görevsizlik kararının kesinleşmesini izleyen günden itibaren otuz gün içinde görevli idari yargı yerinde dava açılabilir.",
    "source": {
      "kind": "generated",
      "styleRef": "2026 SMMM beş seçenekli test",
      "legislationRef": "2577 sayılı İYUK m.9"
    },
    "tags": [
      "Demo Soru",
      "2026 Formatı",
      "Konu Havuzu",
      "Süreler ve Kanun Yolları"
    ],
    "difficulty": "medium",
    "updatedAt": "2026-07-16T00:00:00Z",
    "examPeriod": "2026 test sistemine uyumlu özgün soru",
    "legislationVersion": "2577 sayılı İYUK (16.07.2026)",
    "sourceUpdatedAt": "2026-07-16T00:00:00Z",
    "isPremium": false,
    "isActive": true
  },
  {
    "id": "kh-iy-sure-0019",
    "lessonId": "idari_yargilama_hukuku",
    "topicId": "idari_yargida_sureler_kanun_yollari",
    "question": "Kişi, hakkında dava konusu olabilecek bir işlemin yapılması için idareye başvurmuş; idare cevap vermemiştir. İstek ne zaman reddedilmiş sayılır?",
    "choices": {
      "C": "Otuz gün",
      "A": "Görevsiz adli yargı yerine yapılan başvurunun tarihi hiçbir koşulda korunmaz ve dava daima süreden reddedilir",
      "B": "Kanunda günle belirlenen sürelerin hesabında resmî tatiller tamamen dışarıda bırakılarak yalnız mesai günleri sayılır",
      "D": "Süre bildirimin yapıldığı gün başlar ve hafta sonları hesaba katılmadan yalnız iş günleri üzerinden yürür",
      "E": "Özel kanunda farklı süre olsa bile bütün idari davalarda değişmez biçimde doksan günlük tek süre uygulanır"
    },
    "correctAnswer": "C",
    "explanation": "İYUK m.10'a göre otuz gün içinde cevap verilmezse istek reddedilmiş sayılır.",
    "source": {
      "kind": "generated",
      "styleRef": "2026 SMMM beş seçenekli test",
      "legislationRef": "2577 sayılı İYUK m.10/2"
    },
    "tags": [
      "Demo Soru",
      "2026 Formatı",
      "Konu Havuzu",
      "Süreler ve Kanun Yolları"
    ],
    "difficulty": "medium",
    "updatedAt": "2026-07-16T00:00:00Z",
    "examPeriod": "2026 test sistemine uyumlu özgün soru",
    "legislationVersion": "2577 sayılı İYUK (16.07.2026)",
    "sourceUpdatedAt": "2026-07-16T00:00:00Z",
    "isPremium": false,
    "isActive": true
  },
  {
    "id": "kh-iy-sure-0020",
    "lessonId": "idari_yargilama_hukuku",
    "topicId": "idari_yargida_sureler_kanun_yollari",
    "question": "İYUK m.10 başvurusunda zımni ret süresi kaç gündür?",
    "choices": {
      "C": "Otuz gün",
      "A": "Görevsiz adli yargı yerine yapılan başvurunun tarihi hiçbir koşulda korunmaz ve dava daima süreden reddedilir",
      "B": "Kanunda günle belirlenen sürelerin hesabında resmî tatiller tamamen dışarıda bırakılarak yalnız mesai günleri sayılır",
      "D": "Süre bildirimin yapıldığı gün başlar ve hafta sonları hesaba katılmadan yalnız iş günleri üzerinden yürür",
      "E": "Özel kanunda farklı süre olsa bile bütün idari davalarda değişmez biçimde doksan günlük tek süre uygulanır"
    },
    "correctAnswer": "C",
    "explanation": "İYUK m.10'a göre otuz gün içinde cevap verilmezse istek reddedilmiş sayılır.",
    "source": {
      "kind": "generated",
      "styleRef": "2026 SMMM beş seçenekli test",
      "legislationRef": "2577 sayılı İYUK m.10/2"
    },
    "tags": [
      "Demo Soru",
      "2026 Formatı",
      "Konu Havuzu",
      "Süreler ve Kanun Yolları"
    ],
    "difficulty": "medium",
    "updatedAt": "2026-07-16T00:00:00Z",
    "examPeriod": "2026 test sistemine uyumlu özgün soru",
    "legislationVersion": "2577 sayılı İYUK (16.07.2026)",
    "sourceUpdatedAt": "2026-07-16T00:00:00Z",
    "isPremium": false,
    "isActive": true
  },
  {
    "id": "kh-iy-sure-0021",
    "lessonId": "idari_yargilama_hukuku",
    "topicId": "idari_yargida_sureler_kanun_yollari",
    "question": "İYUK m.10 başvurusuna otuz gün içinde kesin olmayan cevap verilmiştir. İlgili kesin cevabı beklemek isterse azami bekleme süresi nedir?",
    "choices": {
      "A": "Başvuru tarihinden itibaren dört ay",
      "B": "Özel kanunda farklı süre olsa bile bütün idari davalarda değişmez biçimde doksan günlük tek süre uygulanır",
      "C": "Sürenin son günü tatile rastlarsa önceki çalışma gününde sona erer ve sonraki güne uzaması mümkün değildir",
      "D": "Çalışmaya ara verme bütün idari dava sürelerini ara verme boyunca durdurur ve kalan süre sonradan aynen işletilir",
      "E": "İdari makama yapılan her başvuru, kanuni süresi dışında yapılsa bile sona ermiş dava açma süresini yeniden başlatır"
    },
    "correctAnswer": "A",
    "explanation": "Kesin olmayan cevapta dava süresi işlemez; ancak bekleme başvuru tarihinden itibaren dört ayı geçemez.",
    "source": {
      "kind": "generated",
      "styleRef": "2026 SMMM beş seçenekli test",
      "legislationRef": "2577 sayılı İYUK m.10/2"
    },
    "tags": [
      "Demo Soru",
      "2026 Formatı",
      "Konu Havuzu",
      "Süreler ve Kanun Yolları"
    ],
    "difficulty": "hard",
    "updatedAt": "2026-07-16T00:00:00Z",
    "examPeriod": "2026 test sistemine uyumlu özgün soru",
    "legislationVersion": "2577 sayılı İYUK (16.07.2026)",
    "sourceUpdatedAt": "2026-07-16T00:00:00Z",
    "isPremium": false,
    "isActive": true
  },
  {
    "id": "kh-iy-sure-0022",
    "lessonId": "idari_yargilama_hukuku",
    "topicId": "idari_yargida_sureler_kanun_yollari",
    "question": "Kesin olmayan cevaptan sonra kesin cevabı bekleme süresinin üst sınırı nedir?",
    "choices": {
      "C": "Başvuru tarihinden itibaren dört ay",
      "A": "Özel kanunda farklı süre olsa bile bütün idari davalarda değişmez biçimde doksan günlük tek süre uygulanır",
      "B": "Sürenin son günü tatile rastlarsa önceki çalışma gününde sona erer ve sonraki güne uzaması mümkün değildir",
      "D": "Çalışmaya ara verme bütün idari dava sürelerini ara verme boyunca durdurur ve kalan süre sonradan aynen işletilir",
      "E": "İdari makama yapılan her başvuru, kanuni süresi dışında yapılsa bile sona ermiş dava açma süresini yeniden başlatır"
    },
    "correctAnswer": "C",
    "explanation": "Kesin olmayan cevapta dava süresi işlemez; ancak bekleme başvuru tarihinden itibaren dört ayı geçemez.",
    "source": {
      "kind": "generated",
      "styleRef": "2026 SMMM beş seçenekli test",
      "legislationRef": "2577 sayılı İYUK m.10/2"
    },
    "tags": [
      "Demo Soru",
      "2026 Formatı",
      "Konu Havuzu",
      "Süreler ve Kanun Yolları"
    ],
    "difficulty": "hard",
    "updatedAt": "2026-07-16T00:00:00Z",
    "examPeriod": "2026 test sistemine uyumlu özgün soru",
    "legislationVersion": "2577 sayılı İYUK (16.07.2026)",
    "sourceUpdatedAt": "2026-07-16T00:00:00Z",
    "isPremium": false,
    "isActive": true
  },
  {
    "id": "kh-iy-sure-0023",
    "lessonId": "idari_yargilama_hukuku",
    "topicId": "idari_yargida_sureler_kanun_yollari",
    "question": "İYUK m.10 başvurusunda zımni ret sonrası dava açılmamış; idare daha sonra açık cevap vermiştir. Yeni dava imkânı nasıl doğar?",
    "choices": {
      "E": "Cevabın tebliğinden itibaren altmış gün",
      "A": "İdari makama yapılan her başvuru, kanuni süresi dışında yapılsa bile sona ermiş dava açma süresini yeniden başlatır",
      "B": "Yazılı bildirim bulunması hâlinde süre bildirimi izleyen gün değil, işlemin idarece hazırlandığı tarihte başlar",
      "C": "Görevsiz adli yargı yerine yapılan başvurunun tarihi hiçbir koşulda korunmaz ve dava daima süreden reddedilir",
      "D": "Kanunda günle belirlenen sürelerin hesabında resmî tatiller tamamen dışarıda bırakılarak yalnız mesai günleri sayılır"
    },
    "correctAnswer": "E",
    "explanation": "Zımni ret sonrasında yetkili makam cevap verirse, cevabın tebliğinden itibaren altmış gün içinde dava açılabilir.",
    "source": {
      "kind": "generated",
      "styleRef": "2026 SMMM beş seçenekli test",
      "legislationRef": "2577 sayılı İYUK m.10/2"
    },
    "tags": [
      "Demo Soru",
      "2026 Formatı",
      "Konu Havuzu",
      "Süreler ve Kanun Yolları"
    ],
    "difficulty": "hard",
    "updatedAt": "2026-07-16T00:00:00Z",
    "examPeriod": "2026 test sistemine uyumlu özgün soru",
    "legislationVersion": "2577 sayılı İYUK (16.07.2026)",
    "sourceUpdatedAt": "2026-07-16T00:00:00Z",
    "isPremium": false,
    "isActive": true
  },
  {
    "id": "kh-iy-sure-0024",
    "lessonId": "idari_yargilama_hukuku",
    "topicId": "idari_yargida_sureler_kanun_yollari",
    "question": "Zımni retten sonra gelen geç cevaba karşı öngörülen dava süresi nedir?",
    "choices": {
      "E": "Cevabın tebliğinden itibaren altmış gün",
      "A": "İdari makama yapılan her başvuru, kanuni süresi dışında yapılsa bile sona ermiş dava açma süresini yeniden başlatır",
      "B": "Yazılı bildirim bulunması hâlinde süre bildirimi izleyen gün değil, işlemin idarece hazırlandığı tarihte başlar",
      "C": "Görevsiz adli yargı yerine yapılan başvurunun tarihi hiçbir koşulda korunmaz ve dava daima süreden reddedilir",
      "D": "Kanunda günle belirlenen sürelerin hesabında resmî tatiller tamamen dışarıda bırakılarak yalnız mesai günleri sayılır"
    },
    "correctAnswer": "E",
    "explanation": "Zımni ret sonrasında yetkili makam cevap verirse, cevabın tebliğinden itibaren altmış gün içinde dava açılabilir.",
    "source": {
      "kind": "generated",
      "styleRef": "2026 SMMM beş seçenekli test",
      "legislationRef": "2577 sayılı İYUK m.10/2"
    },
    "tags": [
      "Demo Soru",
      "2026 Formatı",
      "Konu Havuzu",
      "Süreler ve Kanun Yolları"
    ],
    "difficulty": "hard",
    "updatedAt": "2026-07-16T00:00:00Z",
    "examPeriod": "2026 test sistemine uyumlu özgün soru",
    "legislationVersion": "2577 sayılı İYUK (16.07.2026)",
    "sourceUpdatedAt": "2026-07-16T00:00:00Z",
    "isPremium": false,
    "isActive": true
  },
  {
    "id": "kh-iy-sure-0025",
    "lessonId": "idari_yargilama_hukuku",
    "topicId": "idari_yargida_sureler_kanun_yollari",
    "question": "Kişi dava açmadan önce işlemin kaldırılmasını üst makamdan istemek istemektedir. Başvuru ne zaman yapılmalıdır?",
    "choices": {
      "B": "Dava açma süresi içinde",
      "A": "Kanunda günle belirlenen sürelerin hesabında resmî tatiller tamamen dışarıda bırakılarak yalnız mesai günleri sayılır",
      "C": "Süre bildirimin yapıldığı gün başlar ve hafta sonları hesaba katılmadan yalnız iş günleri üzerinden yürür",
      "D": "Özel kanunda farklı süre olsa bile bütün idari davalarda değişmez biçimde doksan günlük tek süre uygulanır",
      "E": "Sürenin son günü tatile rastlarsa önceki çalışma gününde sona erer ve sonraki güne uzaması mümkün değildir"
    },
    "correctAnswer": "B",
    "explanation": "Üst makama veya üst makam yoksa işlemi yapan makama başvuru, dava açma süresi içinde yapılmalıdır.",
    "source": {
      "kind": "generated",
      "styleRef": "2026 SMMM beş seçenekli test",
      "legislationRef": "2577 sayılı İYUK m.11/1"
    },
    "tags": [
      "Demo Soru",
      "2026 Formatı",
      "Konu Havuzu",
      "Süreler ve Kanun Yolları"
    ],
    "difficulty": "medium",
    "updatedAt": "2026-07-16T00:00:00Z",
    "examPeriod": "2026 test sistemine uyumlu özgün soru",
    "legislationVersion": "2577 sayılı İYUK (16.07.2026)",
    "sourceUpdatedAt": "2026-07-16T00:00:00Z",
    "isPremium": false,
    "isActive": true
  },
  {
    "id": "kh-iy-sure-0026",
    "lessonId": "idari_yargilama_hukuku",
    "topicId": "idari_yargida_sureler_kanun_yollari",
    "question": "İYUK m.11 kapsamındaki idari başvurunun zaman koşulu hangisidir?",
    "choices": {
      "A": "Dava açma süresi içinde",
      "B": "Kanunda günle belirlenen sürelerin hesabında resmî tatiller tamamen dışarıda bırakılarak yalnız mesai günleri sayılır",
      "C": "Süre bildirimin yapıldığı gün başlar ve hafta sonları hesaba katılmadan yalnız iş günleri üzerinden yürür",
      "D": "Özel kanunda farklı süre olsa bile bütün idari davalarda değişmez biçimde doksan günlük tek süre uygulanır",
      "E": "Sürenin son günü tatile rastlarsa önceki çalışma gününde sona erer ve sonraki güne uzaması mümkün değildir"
    },
    "correctAnswer": "A",
    "explanation": "Üst makama veya üst makam yoksa işlemi yapan makama başvuru, dava açma süresi içinde yapılmalıdır.",
    "source": {
      "kind": "generated",
      "styleRef": "2026 SMMM beş seçenekli test",
      "legislationRef": "2577 sayılı İYUK m.11/1"
    },
    "tags": [
      "Demo Soru",
      "2026 Formatı",
      "Konu Havuzu",
      "Süreler ve Kanun Yolları"
    ],
    "difficulty": "medium",
    "updatedAt": "2026-07-16T00:00:00Z",
    "examPeriod": "2026 test sistemine uyumlu özgün soru",
    "legislationVersion": "2577 sayılı İYUK (16.07.2026)",
    "sourceUpdatedAt": "2026-07-16T00:00:00Z",
    "isPremium": false,
    "isActive": true
  },
  {
    "id": "kh-iy-sure-0027",
    "lessonId": "idari_yargilama_hukuku",
    "topicId": "idari_yargida_sureler_kanun_yollari",
    "question": "İYUK m.11 uyarınca süresinde üst makama başvurulmuştur. İşlemekte olan dava açma süresine etkisi nedir?",
    "choices": {
      "C": "Dava açma süresini durdurur",
      "A": "Sürenin son günü tatile rastlarsa önceki çalışma gününde sona erer ve sonraki güne uzaması mümkün değildir",
      "B": "Çalışmaya ara verme bütün idari dava sürelerini ara verme boyunca durdurur ve kalan süre sonradan aynen işletilir",
      "D": "İdari makama yapılan her başvuru, kanuni süresi dışında yapılsa bile sona ermiş dava açma süresini yeniden başlatır",
      "E": "Yazılı bildirim bulunması hâlinde süre bildirimi izleyen gün değil, işlemin idarece hazırlandığı tarihte başlar"
    },
    "correctAnswer": "C",
    "explanation": "Süresinde yapılan m.11 başvurusu işlemeye başlamış dava açma süresini durdurur.",
    "source": {
      "kind": "generated",
      "styleRef": "2026 SMMM beş seçenekli test",
      "legislationRef": "2577 sayılı İYUK m.11/1"
    },
    "tags": [
      "Demo Soru",
      "2026 Formatı",
      "Konu Havuzu",
      "Süreler ve Kanun Yolları"
    ],
    "difficulty": "easy",
    "updatedAt": "2026-07-16T00:00:00Z",
    "examPeriod": "2026 test sistemine uyumlu özgün soru",
    "legislationVersion": "2577 sayılı İYUK (16.07.2026)",
    "sourceUpdatedAt": "2026-07-16T00:00:00Z",
    "isPremium": false,
    "isActive": true
  },
  {
    "id": "kh-iy-sure-0028",
    "lessonId": "idari_yargilama_hukuku",
    "topicId": "idari_yargida_sureler_kanun_yollari",
    "question": "Üst makama başvurunun dava açma süresine etkisi hangisidir?",
    "choices": {
      "E": "Dava açma süresini durdurur",
      "A": "Sürenin son günü tatile rastlarsa önceki çalışma gününde sona erer ve sonraki güne uzaması mümkün değildir",
      "B": "Çalışmaya ara verme bütün idari dava sürelerini ara verme boyunca durdurur ve kalan süre sonradan aynen işletilir",
      "C": "İdari makama yapılan her başvuru, kanuni süresi dışında yapılsa bile sona ermiş dava açma süresini yeniden başlatır",
      "D": "Yazılı bildirim bulunması hâlinde süre bildirimi izleyen gün değil, işlemin idarece hazırlandığı tarihte başlar"
    },
    "correctAnswer": "E",
    "explanation": "Süresinde yapılan m.11 başvurusu işlemeye başlamış dava açma süresini durdurur.",
    "source": {
      "kind": "generated",
      "styleRef": "2026 SMMM beş seçenekli test",
      "legislationRef": "2577 sayılı İYUK m.11/1"
    },
    "tags": [
      "Demo Soru",
      "2026 Formatı",
      "Konu Havuzu",
      "Süreler ve Kanun Yolları"
    ],
    "difficulty": "easy",
    "updatedAt": "2026-07-16T00:00:00Z",
    "examPeriod": "2026 test sistemine uyumlu özgün soru",
    "legislationVersion": "2577 sayılı İYUK (16.07.2026)",
    "sourceUpdatedAt": "2026-07-16T00:00:00Z",
    "isPremium": false,
    "isActive": true
  },
  {
    "id": "kh-iy-sure-0029",
    "lessonId": "idari_yargilama_hukuku",
    "topicId": "idari_yargida_sureler_kanun_yollari",
    "question": "Üst makam, işlemin kaldırılması başvurusuna cevap vermemiştir. Başvuru ne zaman reddedilmiş sayılır?",
    "choices": {
      "C": "Otuz gün",
      "A": "Yazılı bildirim bulunması hâlinde süre bildirimi izleyen gün değil, işlemin idarece hazırlandığı tarihte başlar",
      "B": "Görevsiz adli yargı yerine yapılan başvurunun tarihi hiçbir koşulda korunmaz ve dava daima süreden reddedilir",
      "D": "Kanunda günle belirlenen sürelerin hesabında resmî tatiller tamamen dışarıda bırakılarak yalnız mesai günleri sayılır",
      "E": "Süre bildirimin yapıldığı gün başlar ve hafta sonları hesaba katılmadan yalnız iş günleri üzerinden yürür"
    },
    "correctAnswer": "C",
    "explanation": "Üst makam başvurusuna otuz gün içinde cevap verilmezse istek reddedilmiş sayılır.",
    "source": {
      "kind": "generated",
      "styleRef": "2026 SMMM beş seçenekli test",
      "legislationRef": "2577 sayılı İYUK m.11/2"
    },
    "tags": [
      "Demo Soru",
      "2026 Formatı",
      "Konu Havuzu",
      "Süreler ve Kanun Yolları"
    ],
    "difficulty": "medium",
    "updatedAt": "2026-07-16T00:00:00Z",
    "examPeriod": "2026 test sistemine uyumlu özgün soru",
    "legislationVersion": "2577 sayılı İYUK (16.07.2026)",
    "sourceUpdatedAt": "2026-07-16T00:00:00Z",
    "isPremium": false,
    "isActive": true
  },
  {
    "id": "kh-iy-sure-0030",
    "lessonId": "idari_yargilama_hukuku",
    "topicId": "idari_yargida_sureler_kanun_yollari",
    "question": "İYUK m.11 başvurusundaki zımni ret süresi kaç gündür?",
    "choices": {
      "D": "Otuz gün",
      "A": "Yazılı bildirim bulunması hâlinde süre bildirimi izleyen gün değil, işlemin idarece hazırlandığı tarihte başlar",
      "B": "Görevsiz adli yargı yerine yapılan başvurunun tarihi hiçbir koşulda korunmaz ve dava daima süreden reddedilir",
      "C": "Kanunda günle belirlenen sürelerin hesabında resmî tatiller tamamen dışarıda bırakılarak yalnız mesai günleri sayılır",
      "E": "Süre bildirimin yapıldığı gün başlar ve hafta sonları hesaba katılmadan yalnız iş günleri üzerinden yürür"
    },
    "correctAnswer": "D",
    "explanation": "Üst makam başvurusuna otuz gün içinde cevap verilmezse istek reddedilmiş sayılır.",
    "source": {
      "kind": "generated",
      "styleRef": "2026 SMMM beş seçenekli test",
      "legislationRef": "2577 sayılı İYUK m.11/2"
    },
    "tags": [
      "Demo Soru",
      "2026 Formatı",
      "Konu Havuzu",
      "Süreler ve Kanun Yolları"
    ],
    "difficulty": "medium",
    "updatedAt": "2026-07-16T00:00:00Z",
    "examPeriod": "2026 test sistemine uyumlu özgün soru",
    "legislationVersion": "2577 sayılı İYUK (16.07.2026)",
    "sourceUpdatedAt": "2026-07-16T00:00:00Z",
    "isPremium": false,
    "isActive": true
  },
  {
    "id": "kh-iy-sure-0031",
    "lessonId": "idari_yargilama_hukuku",
    "topicId": "idari_yargida_sureler_kanun_yollari",
    "question": "İYUK m.11 başvurusu reddedilmiş ve dava süresi yeniden işlemeye başlamıştır. Başvurudan önce geçen süreye ne olur?",
    "choices": {
      "C": "Başvurudan önce geçen süre hesaba katılır",
      "A": "Süre bildirimin yapıldığı gün başlar ve hafta sonları hesaba katılmadan yalnız iş günleri üzerinden yürür",
      "B": "Özel kanunda farklı süre olsa bile bütün idari davalarda değişmez biçimde doksan günlük tek süre uygulanır",
      "D": "Sürenin son günü tatile rastlarsa önceki çalışma gününde sona erer ve sonraki güne uzaması mümkün değildir",
      "E": "Çalışmaya ara verme bütün idari dava sürelerini ara verme boyunca durdurur ve kalan süre sonradan aynen işletilir"
    },
    "correctAnswer": "C",
    "explanation": "Ret veya zımni ret üzerine süre yeniden işler; başvuru tarihine kadar geçmiş olan süre de toplam hesaba dâhil edilir.",
    "source": {
      "kind": "generated",
      "styleRef": "2026 SMMM beş seçenekli test",
      "legislationRef": "2577 sayılı İYUK m.11/3"
    },
    "tags": [
      "Demo Soru",
      "2026 Formatı",
      "Konu Havuzu",
      "Süreler ve Kanun Yolları"
    ],
    "difficulty": "hard",
    "updatedAt": "2026-07-16T00:00:00Z",
    "examPeriod": "2026 test sistemine uyumlu özgün soru",
    "legislationVersion": "2577 sayılı İYUK (16.07.2026)",
    "sourceUpdatedAt": "2026-07-16T00:00:00Z",
    "isPremium": false,
    "isActive": true
  },
  {
    "id": "kh-iy-sure-0032",
    "lessonId": "idari_yargilama_hukuku",
    "topicId": "idari_yargida_sureler_kanun_yollari",
    "question": "M.11 başvurusunun reddinden sonra kalan dava süresi nasıl hesaplanır?",
    "choices": {
      "E": "Başvurudan önce geçen süre hesaba katılır",
      "A": "Süre bildirimin yapıldığı gün başlar ve hafta sonları hesaba katılmadan yalnız iş günleri üzerinden yürür",
      "B": "Özel kanunda farklı süre olsa bile bütün idari davalarda değişmez biçimde doksan günlük tek süre uygulanır",
      "C": "Sürenin son günü tatile rastlarsa önceki çalışma gününde sona erer ve sonraki güne uzaması mümkün değildir",
      "D": "Çalışmaya ara verme bütün idari dava sürelerini ara verme boyunca durdurur ve kalan süre sonradan aynen işletilir"
    },
    "correctAnswer": "E",
    "explanation": "Ret veya zımni ret üzerine süre yeniden işler; başvuru tarihine kadar geçmiş olan süre de toplam hesaba dâhil edilir.",
    "source": {
      "kind": "generated",
      "styleRef": "2026 SMMM beş seçenekli test",
      "legislationRef": "2577 sayılı İYUK m.11/3"
    },
    "tags": [
      "Demo Soru",
      "2026 Formatı",
      "Konu Havuzu",
      "Süreler ve Kanun Yolları"
    ],
    "difficulty": "hard",
    "updatedAt": "2026-07-16T00:00:00Z",
    "examPeriod": "2026 test sistemine uyumlu özgün soru",
    "legislationVersion": "2577 sayılı İYUK (16.07.2026)",
    "sourceUpdatedAt": "2026-07-16T00:00:00Z",
    "isPremium": false,
    "isActive": true
  },
  {
    "id": "kh-iy-sure-0033",
    "lessonId": "idari_yargilama_hukuku",
    "topicId": "idari_yargida_sureler_kanun_yollari",
    "question": "Bir idari işleme karşı iptal davası açılmıştır. Yalnız dava açılması işlemin uygulanmasını durdurur mu?",
    "choices": {
      "B": "Yürütmeyi kendiliğinden durdurmaz",
      "A": "Yürütmenin durdurulması istemi yalnız dava açılmadan önce yapılabilir; dava dilekçesinde ileri sürülmesi yasaktır",
      "C": "İtiraz üzerine verilen yürütmenin durdurulması kararı aynı merci önünde sınırsız sayıda yeniden incelenebilir",
      "D": "Atama ve naklen atama işlemleri kanun gereği her zaman uygulanmakla etkisi tükenecek işlem kabul edilir",
      "E": "Vergi davası açılması hiçbir durumda dava konusu tahsil işlemini etkilemez ve yürütmenin durdurulması da istenemez"
    },
    "correctAnswer": "B",
    "explanation": "İdari dava açılması, kanundaki özel hâller dışında işlemin yürütülmesini kendiliğinden durdurmaz.",
    "source": {
      "kind": "generated",
      "styleRef": "2026 SMMM beş seçenekli test",
      "legislationRef": "2577 sayılı İYUK m.27/1"
    },
    "tags": [
      "Demo Soru",
      "2026 Formatı",
      "Konu Havuzu",
      "Süreler ve Kanun Yolları"
    ],
    "difficulty": "easy",
    "updatedAt": "2026-07-16T00:00:00Z",
    "examPeriod": "2026 test sistemine uyumlu özgün soru",
    "legislationVersion": "2577 sayılı İYUK (16.07.2026)",
    "sourceUpdatedAt": "2026-07-16T00:00:00Z",
    "isPremium": false,
    "isActive": true
  },
  {
    "id": "kh-iy-sure-0034",
    "lessonId": "idari_yargilama_hukuku",
    "topicId": "idari_yargida_sureler_kanun_yollari",
    "question": "İdari dava açılmasının işlemin yürütmesine genel etkisi hangisidir?",
    "choices": {
      "D": "Yürütmeyi kendiliğinden durdurmaz",
      "A": "Yürütmenin durdurulması istemi yalnız dava açılmadan önce yapılabilir; dava dilekçesinde ileri sürülmesi yasaktır",
      "B": "İtiraz üzerine verilen yürütmenin durdurulması kararı aynı merci önünde sınırsız sayıda yeniden incelenebilir",
      "C": "Atama ve naklen atama işlemleri kanun gereği her zaman uygulanmakla etkisi tükenecek işlem kabul edilir",
      "E": "Vergi davası açılması hiçbir durumda dava konusu tahsil işlemini etkilemez ve yürütmenin durdurulması da istenemez"
    },
    "correctAnswer": "D",
    "explanation": "İdari dava açılması, kanundaki özel hâller dışında işlemin yürütülmesini kendiliğinden durdurmaz.",
    "source": {
      "kind": "generated",
      "styleRef": "2026 SMMM beş seçenekli test",
      "legislationRef": "2577 sayılı İYUK m.27/1"
    },
    "tags": [
      "Demo Soru",
      "2026 Formatı",
      "Konu Havuzu",
      "Süreler ve Kanun Yolları"
    ],
    "difficulty": "easy",
    "updatedAt": "2026-07-16T00:00:00Z",
    "examPeriod": "2026 test sistemine uyumlu özgün soru",
    "legislationVersion": "2577 sayılı İYUK (16.07.2026)",
    "sourceUpdatedAt": "2026-07-16T00:00:00Z",
    "isPremium": false,
    "isActive": true
  },
  {
    "id": "kh-iy-sure-0035",
    "lessonId": "idari_yargilama_hukuku",
    "topicId": "idari_yargida_sureler_kanun_yollari",
    "question": "İşlem açıkça hukuka aykırıdır ancak uygulanması telafisi güç zarar doğurmayacaktır. Genel kurala göre yürütme durdurulabilir mi?",
    "choices": {
      "A": "Açık hukuka aykırılık ve telafisi güç zarar",
      "B": "Vergi davası açılması hiçbir durumda dava konusu tahsil işlemini etkilemez ve yürütmenin durdurulması da istenemez",
      "C": "Aynı sebeplere dayanılarak yürütmenin durdurulması istemi reddedilse bile sınırsız kez tekrarlanabilir",
      "D": "İdari dava açılması bütün işlemlerin yürütmesini kendiliğinden durdurur ve ayrıca mahkeme kararı gerekmez",
      "E": "Yürütmenin durdurulması için yalnız işlemin hukuka aykırı görünmesi yeterlidir; zarar koşulu hiçbir zaman aranmaz"
    },
    "correctAnswer": "A",
    "explanation": "Genel yürütmenin durdurulması kararı için açık hukuka aykırılık ile telafisi güç veya imkânsız zarar koşulları birlikte gerekir.",
    "source": {
      "kind": "generated",
      "styleRef": "2026 SMMM beş seçenekli test",
      "legislationRef": "2577 sayılı İYUK m.27/2"
    },
    "tags": [
      "Demo Soru",
      "2026 Formatı",
      "Konu Havuzu",
      "Süreler ve Kanun Yolları"
    ],
    "difficulty": "medium",
    "updatedAt": "2026-07-16T00:00:00Z",
    "examPeriod": "2026 test sistemine uyumlu özgün soru",
    "legislationVersion": "2577 sayılı İYUK (16.07.2026)",
    "sourceUpdatedAt": "2026-07-16T00:00:00Z",
    "isPremium": false,
    "isActive": true
  },
  {
    "id": "kh-iy-sure-0036",
    "lessonId": "idari_yargilama_hukuku",
    "topicId": "idari_yargida_sureler_kanun_yollari",
    "question": "Yürütmenin durdurulması için birlikte gerçekleşmesi gereken iki koşul hangisidir?",
    "choices": {
      "A": "Açık hukuka aykırılık ve telafisi güç zarar",
      "B": "Vergi davası açılması hiçbir durumda dava konusu tahsil işlemini etkilemez ve yürütmenin durdurulması da istenemez",
      "C": "Aynı sebeplere dayanılarak yürütmenin durdurulması istemi reddedilse bile sınırsız kez tekrarlanabilir",
      "D": "İdari dava açılması bütün işlemlerin yürütmesini kendiliğinden durdurur ve ayrıca mahkeme kararı gerekmez",
      "E": "Yürütmenin durdurulması için yalnız işlemin hukuka aykırı görünmesi yeterlidir; zarar koşulu hiçbir zaman aranmaz"
    },
    "correctAnswer": "A",
    "explanation": "Genel yürütmenin durdurulması kararı için açık hukuka aykırılık ile telafisi güç veya imkânsız zarar koşulları birlikte gerekir.",
    "source": {
      "kind": "generated",
      "styleRef": "2026 SMMM beş seçenekli test",
      "legislationRef": "2577 sayılı İYUK m.27/2"
    },
    "tags": [
      "Demo Soru",
      "2026 Formatı",
      "Konu Havuzu",
      "Süreler ve Kanun Yolları"
    ],
    "difficulty": "medium",
    "updatedAt": "2026-07-16T00:00:00Z",
    "examPeriod": "2026 test sistemine uyumlu özgün soru",
    "legislationVersion": "2577 sayılı İYUK (16.07.2026)",
    "sourceUpdatedAt": "2026-07-16T00:00:00Z",
    "isPremium": false,
    "isActive": true
  },
  {
    "id": "kh-iy-sure-0037",
    "lessonId": "idari_yargilama_hukuku",
    "topicId": "idari_yargida_sureler_kanun_yollari",
    "question": "Mahkeme yürütmenin durdurulmasına karar verirken yalnız 'koşullar oluşmuştur' demiştir. Kararda ayrıca ne gösterilmelidir?",
    "choices": {
      "D": "Hukuka aykırılık ve telafisi güç zarar somutlaştırılmalıdır",
      "A": "Yürütmenin durdurulması için yalnız işlemin hukuka aykırı görünmesi yeterlidir; zarar koşulu hiçbir zaman aranmaz",
      "B": "Mahkeme koşulları göstermeden tek cümlelik ara kararla yürütmeyi durdurabilir ve gerekçe yazmak zorunda değildir",
      "C": "Yürütmenin durdurulması istemi yalnız dava açılmadan önce yapılabilir; dava dilekçesinde ileri sürülmesi yasaktır",
      "E": "İtiraz üzerine verilen yürütmenin durdurulması kararı aynı merci önünde sınırsız sayıda yeniden incelenebilir"
    },
    "correctAnswer": "D",
    "explanation": "Kararda işlemin hangi gerekçelerle açıkça hukuka aykırı olduğu ve doğacak telafisi güç zararın ne olduğu belirtilmelidir.",
    "source": {
      "kind": "generated",
      "styleRef": "2026 SMMM beş seçenekli test",
      "legislationRef": "2577 sayılı İYUK m.27/2"
    },
    "tags": [
      "Demo Soru",
      "2026 Formatı",
      "Konu Havuzu",
      "Süreler ve Kanun Yolları"
    ],
    "difficulty": "medium",
    "updatedAt": "2026-07-16T00:00:00Z",
    "examPeriod": "2026 test sistemine uyumlu özgün soru",
    "legislationVersion": "2577 sayılı İYUK (16.07.2026)",
    "sourceUpdatedAt": "2026-07-16T00:00:00Z",
    "isPremium": false,
    "isActive": true
  },
  {
    "id": "kh-iy-sure-0038",
    "lessonId": "idari_yargilama_hukuku",
    "topicId": "idari_yargida_sureler_kanun_yollari",
    "question": "Yürütmenin durdurulması kararının gerekçe içeriği için zorunlu olan nedir?",
    "choices": {
      "B": "Hukuka aykırılık ve telafisi güç zarar somutlaştırılmalıdır",
      "A": "Yürütmenin durdurulması için yalnız işlemin hukuka aykırı görünmesi yeterlidir; zarar koşulu hiçbir zaman aranmaz",
      "C": "Mahkeme koşulları göstermeden tek cümlelik ara kararla yürütmeyi durdurabilir ve gerekçe yazmak zorunda değildir",
      "D": "Yürütmenin durdurulması istemi yalnız dava açılmadan önce yapılabilir; dava dilekçesinde ileri sürülmesi yasaktır",
      "E": "İtiraz üzerine verilen yürütmenin durdurulması kararı aynı merci önünde sınırsız sayıda yeniden incelenebilir"
    },
    "correctAnswer": "B",
    "explanation": "Kararda işlemin hangi gerekçelerle açıkça hukuka aykırı olduğu ve doğacak telafisi güç zararın ne olduğu belirtilmelidir.",
    "source": {
      "kind": "generated",
      "styleRef": "2026 SMMM beş seçenekli test",
      "legislationRef": "2577 sayılı İYUK m.27/2"
    },
    "tags": [
      "Demo Soru",
      "2026 Formatı",
      "Konu Havuzu",
      "Süreler ve Kanun Yolları"
    ],
    "difficulty": "medium",
    "updatedAt": "2026-07-16T00:00:00Z",
    "examPeriod": "2026 test sistemine uyumlu özgün soru",
    "legislationVersion": "2577 sayılı İYUK (16.07.2026)",
    "sourceUpdatedAt": "2026-07-16T00:00:00Z",
    "isPremium": false,
    "isActive": true
  },
  {
    "id": "kh-iy-sure-0039",
    "lessonId": "idari_yargilama_hukuku",
    "topicId": "idari_yargida_sureler_kanun_yollari",
    "question": "Uygulanmakla etkisi tükenecek işlem için acil yürütmenin durdurulması istenmiştir. Savunma alınmadan geçici karar mümkün müdür?",
    "choices": {
      "B": "Savunmadan sonra yeniden karar verilmek üzere durdurulabilir",
      "A": "İtiraz üzerine verilen yürütmenin durdurulması kararı aynı merci önünde sınırsız sayıda yeniden incelenebilir",
      "C": "Atama ve naklen atama işlemleri kanun gereği her zaman uygulanmakla etkisi tükenecek işlem kabul edilir",
      "D": "Vergi davası açılması hiçbir durumda dava konusu tahsil işlemini etkilemez ve yürütmenin durdurulması da istenemez",
      "E": "Aynı sebeplere dayanılarak yürütmenin durdurulması istemi reddedilse bile sınırsız kez tekrarlanabilir"
    },
    "correctAnswer": "B",
    "explanation": "Etkisi uygulanmakla tükenecek işlemin yürütmesi, savunma alındıktan sonra yeniden karar verilmek üzere savunma öncesinde durdurulabilir.",
    "source": {
      "kind": "generated",
      "styleRef": "2026 SMMM beş seçenekli test",
      "legislationRef": "2577 sayılı İYUK m.27/2"
    },
    "tags": [
      "Demo Soru",
      "2026 Formatı",
      "Konu Havuzu",
      "Süreler ve Kanun Yolları"
    ],
    "difficulty": "hard",
    "updatedAt": "2026-07-16T00:00:00Z",
    "examPeriod": "2026 test sistemine uyumlu özgün soru",
    "legislationVersion": "2577 sayılı İYUK (16.07.2026)",
    "sourceUpdatedAt": "2026-07-16T00:00:00Z",
    "isPremium": false,
    "isActive": true
  },
  {
    "id": "kh-iy-sure-0040",
    "lessonId": "idari_yargilama_hukuku",
    "topicId": "idari_yargida_sureler_kanun_yollari",
    "question": "Uygulanmakla etkisi tükenecek işlemde savunma alınmadan verilen kararın niteliği hangisidir?",
    "choices": {
      "E": "Savunmadan sonra yeniden karar verilmek üzere durdurulabilir",
      "A": "İtiraz üzerine verilen yürütmenin durdurulması kararı aynı merci önünde sınırsız sayıda yeniden incelenebilir",
      "B": "Atama ve naklen atama işlemleri kanun gereği her zaman uygulanmakla etkisi tükenecek işlem kabul edilir",
      "C": "Vergi davası açılması hiçbir durumda dava konusu tahsil işlemini etkilemez ve yürütmenin durdurulması da istenemez",
      "D": "Aynı sebeplere dayanılarak yürütmenin durdurulması istemi reddedilse bile sınırsız kez tekrarlanabilir"
    },
    "correctAnswer": "E",
    "explanation": "Etkisi uygulanmakla tükenecek işlemin yürütmesi, savunma alındıktan sonra yeniden karar verilmek üzere savunma öncesinde durdurulabilir.",
    "source": {
      "kind": "generated",
      "styleRef": "2026 SMMM beş seçenekli test",
      "legislationRef": "2577 sayılı İYUK m.27/2"
    },
    "tags": [
      "Demo Soru",
      "2026 Formatı",
      "Konu Havuzu",
      "Süreler ve Kanun Yolları"
    ],
    "difficulty": "hard",
    "updatedAt": "2026-07-16T00:00:00Z",
    "examPeriod": "2026 test sistemine uyumlu özgün soru",
    "legislationVersion": "2577 sayılı İYUK (16.07.2026)",
    "sourceUpdatedAt": "2026-07-16T00:00:00Z",
    "isPremium": false,
    "isActive": true
  },
  {
    "id": "kh-iy-sure-0041",
    "lessonId": "idari_yargilama_hukuku",
    "topicId": "idari_yargida_sureler_kanun_yollari",
    "question": "Tarh edilen vergiye karşı vergi mahkemesinde dava açılmıştır. Dava konusu bölümün tahsil işlemi kural olarak ne olur?",
    "choices": {
      "A": "Tahsil işlemi durur",
      "B": "Aynı sebeplere dayanılarak yürütmenin durdurulması istemi reddedilse bile sınırsız kez tekrarlanabilir",
      "C": "İdari dava açılması bütün işlemlerin yürütmesini kendiliğinden durdurur ve ayrıca mahkeme kararı gerekmez",
      "D": "Yürütmenin durdurulması için yalnız işlemin hukuka aykırı görünmesi yeterlidir; zarar koşulu hiçbir zaman aranmaz",
      "E": "Mahkeme koşulları göstermeden tek cümlelik ara kararla yürütmeyi durdurabilir ve gerekçe yazmak zorunda değildir"
    },
    "correctAnswer": "A",
    "explanation": "Vergi mahkemesinde vergi uyuşmazlığından doğan davanın açılması, dava konusu edilen bölümün tahsil işlemini kural olarak durdurur.",
    "source": {
      "kind": "generated",
      "styleRef": "2026 SMMM beş seçenekli test",
      "legislationRef": "2577 sayılı İYUK m.27/4"
    },
    "tags": [
      "Demo Soru",
      "2026 Formatı",
      "Konu Havuzu",
      "Süreler ve Kanun Yolları"
    ],
    "difficulty": "medium",
    "updatedAt": "2026-07-16T00:00:00Z",
    "examPeriod": "2026 test sistemine uyumlu özgün soru",
    "legislationVersion": "2577 sayılı İYUK (16.07.2026)",
    "sourceUpdatedAt": "2026-07-16T00:00:00Z",
    "isPremium": false,
    "isActive": true
  },
  {
    "id": "kh-iy-sure-0042",
    "lessonId": "idari_yargilama_hukuku",
    "topicId": "idari_yargida_sureler_kanun_yollari",
    "question": "Vergi davasının dava konusu tahsil işlemine genel etkisi hangisidir?",
    "choices": {
      "E": "Tahsil işlemi durur",
      "A": "Aynı sebeplere dayanılarak yürütmenin durdurulması istemi reddedilse bile sınırsız kez tekrarlanabilir",
      "B": "İdari dava açılması bütün işlemlerin yürütmesini kendiliğinden durdurur ve ayrıca mahkeme kararı gerekmez",
      "C": "Yürütmenin durdurulması için yalnız işlemin hukuka aykırı görünmesi yeterlidir; zarar koşulu hiçbir zaman aranmaz",
      "D": "Mahkeme koşulları göstermeden tek cümlelik ara kararla yürütmeyi durdurabilir ve gerekçe yazmak zorunda değildir"
    },
    "correctAnswer": "E",
    "explanation": "Vergi mahkemesinde vergi uyuşmazlığından doğan davanın açılması, dava konusu edilen bölümün tahsil işlemini kural olarak durdurur.",
    "source": {
      "kind": "generated",
      "styleRef": "2026 SMMM beş seçenekli test",
      "legislationRef": "2577 sayılı İYUK m.27/4"
    },
    "tags": [
      "Demo Soru",
      "2026 Formatı",
      "Konu Havuzu",
      "Süreler ve Kanun Yolları"
    ],
    "difficulty": "medium",
    "updatedAt": "2026-07-16T00:00:00Z",
    "examPeriod": "2026 test sistemine uyumlu özgün soru",
    "legislationVersion": "2577 sayılı İYUK (16.07.2026)",
    "sourceUpdatedAt": "2026-07-16T00:00:00Z",
    "isPremium": false,
    "isActive": true
  },
  {
    "id": "kh-iy-sure-0043",
    "lessonId": "idari_yargilama_hukuku",
    "topicId": "idari_yargida_sureler_kanun_yollari",
    "question": "İdare mahkemesinin yürütmenin durdurulması kararına karşı başvuru yapılacaktır. Genel itiraz süresi ve sayısı nedir?",
    "choices": {
      "A": "Yedi gün içinde bir defa",
      "B": "Mahkeme koşulları göstermeden tek cümlelik ara kararla yürütmeyi durdurabilir ve gerekçe yazmak zorunda değildir",
      "C": "Yürütmenin durdurulması istemi yalnız dava açılmadan önce yapılabilir; dava dilekçesinde ileri sürülmesi yasaktır",
      "D": "İtiraz üzerine verilen yürütmenin durdurulması kararı aynı merci önünde sınırsız sayıda yeniden incelenebilir",
      "E": "Atama ve naklen atama işlemleri kanun gereği her zaman uygulanmakla etkisi tükenecek işlem kabul edilir"
    },
    "correctAnswer": "A",
    "explanation": "Yürütmenin durdurulması kararına tebliği izleyen günden itibaren yedi gün içinde bir defaya mahsus itiraz edilebilir.",
    "source": {
      "kind": "generated",
      "styleRef": "2026 SMMM beş seçenekli test",
      "legislationRef": "2577 sayılı İYUK m.27/7"
    },
    "tags": [
      "Demo Soru",
      "2026 Formatı",
      "Konu Havuzu",
      "Süreler ve Kanun Yolları"
    ],
    "difficulty": "medium",
    "updatedAt": "2026-07-16T00:00:00Z",
    "examPeriod": "2026 test sistemine uyumlu özgün soru",
    "legislationVersion": "2577 sayılı İYUK (16.07.2026)",
    "sourceUpdatedAt": "2026-07-16T00:00:00Z",
    "isPremium": false,
    "isActive": true
  },
  {
    "id": "kh-iy-sure-0044",
    "lessonId": "idari_yargilama_hukuku",
    "topicId": "idari_yargida_sureler_kanun_yollari",
    "question": "Yürütmenin durdurulması kararına itirazın yapısal sınırı hangisidir?",
    "choices": {
      "D": "Yedi gün içinde bir defa",
      "A": "Mahkeme koşulları göstermeden tek cümlelik ara kararla yürütmeyi durdurabilir ve gerekçe yazmak zorunda değildir",
      "B": "Yürütmenin durdurulması istemi yalnız dava açılmadan önce yapılabilir; dava dilekçesinde ileri sürülmesi yasaktır",
      "C": "İtiraz üzerine verilen yürütmenin durdurulması kararı aynı merci önünde sınırsız sayıda yeniden incelenebilir",
      "E": "Atama ve naklen atama işlemleri kanun gereği her zaman uygulanmakla etkisi tükenecek işlem kabul edilir"
    },
    "correctAnswer": "D",
    "explanation": "Yürütmenin durdurulması kararına tebliği izleyen günden itibaren yedi gün içinde bir defaya mahsus itiraz edilebilir.",
    "source": {
      "kind": "generated",
      "styleRef": "2026 SMMM beş seçenekli test",
      "legislationRef": "2577 sayılı İYUK m.27/7"
    },
    "tags": [
      "Demo Soru",
      "2026 Formatı",
      "Konu Havuzu",
      "Süreler ve Kanun Yolları"
    ],
    "difficulty": "medium",
    "updatedAt": "2026-07-16T00:00:00Z",
    "examPeriod": "2026 test sistemine uyumlu özgün soru",
    "legislationVersion": "2577 sayılı İYUK (16.07.2026)",
    "sourceUpdatedAt": "2026-07-16T00:00:00Z",
    "isPremium": false,
    "isActive": true
  },
  {
    "id": "kh-iy-sure-0045",
    "lessonId": "idari_yargilama_hukuku",
    "topicId": "idari_yargida_sureler_kanun_yollari",
    "question": "İdare mahkemesi kararı olağan istinafa açıktır. Başvuru hangi süre içinde ve nereye yapılır?",
    "choices": {
      "D": "Otuz gün içinde bölge idare mahkemesine",
      "A": "İvedi yargılama usulündeki kararlar önce istinafa, ardından aynı dosya üzerinden yeniden ilk derece mahkemesine gider",
      "B": "Temyiz yalnız tarafların sözlü beyanıyla yapılır; dilekçe ve kanuni başvuru süresi aranmaz",
      "C": "Yargılamanın yenilenmesi kanunda sayılan sebeplere bağlı değildir ve kesinleşen her karar için süre sınırı olmadan istenebilir",
      "E": "İstinaf başvurusu doğrudan Danıştay Genel Kurulunca ilk derece incelemesi yapılarak kesin karara bağlanır"
    },
    "correctAnswer": "D",
    "explanation": "İstinaf, kararın tebliğinden itibaren otuz gün içinde mahkemenin bulunduğu çevredeki bölge idare mahkemesine yapılır.",
    "source": {
      "kind": "generated",
      "styleRef": "2026 SMMM beş seçenekli test",
      "legislationRef": "2577 sayılı İYUK m.45/1"
    },
    "tags": [
      "Demo Soru",
      "2026 Formatı",
      "Konu Havuzu",
      "Süreler ve Kanun Yolları"
    ],
    "difficulty": "easy",
    "updatedAt": "2026-07-16T00:00:00Z",
    "examPeriod": "2026 test sistemine uyumlu özgün soru",
    "legislationVersion": "2577 sayılı İYUK (16.07.2026)",
    "sourceUpdatedAt": "2026-07-16T00:00:00Z",
    "isPremium": false,
    "isActive": true
  },
  {
    "id": "kh-iy-sure-0046",
    "lessonId": "idari_yargilama_hukuku",
    "topicId": "idari_yargida_sureler_kanun_yollari",
    "question": "İstinaf başvurusunun genel süresi ve inceleme mercii hangisidir?",
    "choices": {
      "A": "Otuz gün içinde bölge idare mahkemesine",
      "B": "İvedi yargılama usulündeki kararlar önce istinafa, ardından aynı dosya üzerinden yeniden ilk derece mahkemesine gider",
      "C": "Temyiz yalnız tarafların sözlü beyanıyla yapılır; dilekçe ve kanuni başvuru süresi aranmaz",
      "D": "Yargılamanın yenilenmesi kanunda sayılan sebeplere bağlı değildir ve kesinleşen her karar için süre sınırı olmadan istenebilir",
      "E": "İstinaf başvurusu doğrudan Danıştay Genel Kurulunca ilk derece incelemesi yapılarak kesin karara bağlanır"
    },
    "correctAnswer": "A",
    "explanation": "İstinaf, kararın tebliğinden itibaren otuz gün içinde mahkemenin bulunduğu çevredeki bölge idare mahkemesine yapılır.",
    "source": {
      "kind": "generated",
      "styleRef": "2026 SMMM beş seçenekli test",
      "legislationRef": "2577 sayılı İYUK m.45/1"
    },
    "tags": [
      "Demo Soru",
      "2026 Formatı",
      "Konu Havuzu",
      "Süreler ve Kanun Yolları"
    ],
    "difficulty": "easy",
    "updatedAt": "2026-07-16T00:00:00Z",
    "examPeriod": "2026 test sistemine uyumlu özgün soru",
    "legislationVersion": "2577 sayılı İYUK (16.07.2026)",
    "sourceUpdatedAt": "2026-07-16T00:00:00Z",
    "isPremium": false,
    "isActive": true
  },
  {
    "id": "kh-iy-sure-0047",
    "lessonId": "idari_yargilama_hukuku",
    "topicId": "idari_yargida_sureler_kanun_yollari",
    "question": "Bölge idare mahkemesinin İYUK m.46'da sayılan temyize açık kararına başvurulacaktır. Genel süre ve merci hangisidir?",
    "choices": {
      "B": "Otuz gün içinde Danıştaya",
      "A": "İstinaf başvurusu doğrudan Danıştay Genel Kurulunca ilk derece incelemesi yapılarak kesin karara bağlanır",
      "C": "Temyiz incelemesinde Danıştay idarenin takdir yetkisini kullanarak uyuşmazlığa konu yeni işlemi kendisi tesis eder",
      "D": "Kanun yoluna başvurulması ilk derece kararının yürütülmesini her durumda kendiliğinden durdurur",
      "E": "Bölge idare mahkemesi istinafta hukuka aykırı kararı saptasa bile yalnız dosyayı kapatabilir, esas hakkında karar veremez"
    },
    "correctAnswer": "B",
    "explanation": "İYUK m.46 kapsamındaki kararlar tebliğden itibaren otuz gün içinde Danıştayda temyiz edilebilir.",
    "source": {
      "kind": "generated",
      "styleRef": "2026 SMMM beş seçenekli test",
      "legislationRef": "2577 sayılı İYUK m.46"
    },
    "tags": [
      "Demo Soru",
      "2026 Formatı",
      "Konu Havuzu",
      "Süreler ve Kanun Yolları"
    ],
    "difficulty": "medium",
    "updatedAt": "2026-07-16T00:00:00Z",
    "examPeriod": "2026 test sistemine uyumlu özgün soru",
    "legislationVersion": "2577 sayılı İYUK (16.07.2026)",
    "sourceUpdatedAt": "2026-07-16T00:00:00Z",
    "isPremium": false,
    "isActive": true
  },
  {
    "id": "kh-iy-sure-0048",
    "lessonId": "idari_yargilama_hukuku",
    "topicId": "idari_yargida_sureler_kanun_yollari",
    "question": "İdari yargıda temyizin genel süresi ve inceleme mercii hangisidir?",
    "choices": {
      "D": "Otuz gün içinde Danıştaya",
      "A": "İstinaf başvurusu doğrudan Danıştay Genel Kurulunca ilk derece incelemesi yapılarak kesin karara bağlanır",
      "B": "Temyiz incelemesinde Danıştay idarenin takdir yetkisini kullanarak uyuşmazlığa konu yeni işlemi kendisi tesis eder",
      "C": "Kanun yoluna başvurulması ilk derece kararının yürütülmesini her durumda kendiliğinden durdurur",
      "E": "Bölge idare mahkemesi istinafta hukuka aykırı kararı saptasa bile yalnız dosyayı kapatabilir, esas hakkında karar veremez"
    },
    "correctAnswer": "D",
    "explanation": "İYUK m.46 kapsamındaki kararlar tebliğden itibaren otuz gün içinde Danıştayda temyiz edilebilir.",
    "source": {
      "kind": "generated",
      "styleRef": "2026 SMMM beş seçenekli test",
      "legislationRef": "2577 sayılı İYUK m.46"
    },
    "tags": [
      "Demo Soru",
      "2026 Formatı",
      "Konu Havuzu",
      "Süreler ve Kanun Yolları"
    ],
    "difficulty": "medium",
    "updatedAt": "2026-07-16T00:00:00Z",
    "examPeriod": "2026 test sistemine uyumlu özgün soru",
    "legislationVersion": "2577 sayılı İYUK (16.07.2026)",
    "sourceUpdatedAt": "2026-07-16T00:00:00Z",
    "isPremium": false,
    "isActive": true
  },
  {
    "id": "kh-iy-sure-0049",
    "lessonId": "idari_yargilama_hukuku",
    "topicId": "idari_yargida_sureler_kanun_yollari",
    "question": "İlk derece kararı hakkında istinaf başvurusu yapılmıştır. Başvuru tek başına kararın yürütülmesini durdurur mu?",
    "choices": {
      "E": "Kendiliğinden durdurmaz",
      "A": "Bölge idare mahkemesi istinafta hukuka aykırı kararı saptasa bile yalnız dosyayı kapatabilir, esas hakkında karar veremez",
      "B": "Kanun yararına bozma daha önce kesinleşmiş kararın taraflar arasındaki bütün hukuki sonuçlarını geriye etkili kaldırır",
      "C": "İvedi yargılama usulündeki kararlar önce istinafa, ardından aynı dosya üzerinden yeniden ilk derece mahkemesine gider",
      "D": "Temyiz yalnız tarafların sözlü beyanıyla yapılır; dilekçe ve kanuni başvuru süresi aranmaz"
    },
    "correctAnswer": "E",
    "explanation": "İstinaf veya temyiz yoluna başvurulması, mahkeme kararının yürütülmesini kendiliğinden durdurmaz; ayrıca karar gerekir.",
    "source": {
      "kind": "generated",
      "styleRef": "2026 SMMM beş seçenekli test",
      "legislationRef": "2577 sayılı İYUK m.52/1"
    },
    "tags": [
      "Demo Soru",
      "2026 Formatı",
      "Konu Havuzu",
      "Süreler ve Kanun Yolları"
    ],
    "difficulty": "medium",
    "updatedAt": "2026-07-16T00:00:00Z",
    "examPeriod": "2026 test sistemine uyumlu özgün soru",
    "legislationVersion": "2577 sayılı İYUK (16.07.2026)",
    "sourceUpdatedAt": "2026-07-16T00:00:00Z",
    "isPremium": false,
    "isActive": true
  },
  {
    "id": "kh-iy-sure-0050",
    "lessonId": "idari_yargilama_hukuku",
    "topicId": "idari_yargida_sureler_kanun_yollari",
    "question": "İstinaf veya temyiz başvurusunun kararın yürütmesine genel etkisi hangisidir?",
    "choices": {
      "C": "Kendiliğinden durdurmaz",
      "A": "Bölge idare mahkemesi istinafta hukuka aykırı kararı saptasa bile yalnız dosyayı kapatabilir, esas hakkında karar veremez",
      "B": "Kanun yararına bozma daha önce kesinleşmiş kararın taraflar arasındaki bütün hukuki sonuçlarını geriye etkili kaldırır",
      "D": "İvedi yargılama usulündeki kararlar önce istinafa, ardından aynı dosya üzerinden yeniden ilk derece mahkemesine gider",
      "E": "Temyiz yalnız tarafların sözlü beyanıyla yapılır; dilekçe ve kanuni başvuru süresi aranmaz"
    },
    "correctAnswer": "C",
    "explanation": "İstinaf veya temyiz yoluna başvurulması, mahkeme kararının yürütülmesini kendiliğinden durdurmaz; ayrıca karar gerekir.",
    "source": {
      "kind": "generated",
      "styleRef": "2026 SMMM beş seçenekli test",
      "legislationRef": "2577 sayılı İYUK m.52/1"
    },
    "tags": [
      "Demo Soru",
      "2026 Formatı",
      "Konu Havuzu",
      "Süreler ve Kanun Yolları"
    ],
    "difficulty": "medium",
    "updatedAt": "2026-07-16T00:00:00Z",
    "examPeriod": "2026 test sistemine uyumlu özgün soru",
    "legislationVersion": "2577 sayılı İYUK (16.07.2026)",
    "sourceUpdatedAt": "2026-07-16T00:00:00Z",
    "isPremium": false,
    "isActive": true
  },
  {
    "id": "kh-iy-sure-0051",
    "lessonId": "idari_yargilama_hukuku",
    "topicId": "idari_yargida_sureler_kanun_yollari",
    "question": "Kesinleşmiş bir karar kanun yararına temyiz sonucunda bozulmuştur. Bu bozmanın taraflar arasındaki önceki sonuca etkisi nedir?",
    "choices": {
      "A": "Kesinleşmiş kararın hukuki sonuçlarını kaldırmaz",
      "B": "Temyiz yalnız tarafların sözlü beyanıyla yapılır; dilekçe ve kanuni başvuru süresi aranmaz",
      "C": "Yargılamanın yenilenmesi kanunda sayılan sebeplere bağlı değildir ve kesinleşen her karar için süre sınırı olmadan istenebilir",
      "D": "İstinaf başvurusu doğrudan Danıştay Genel Kurulunca ilk derece incelemesi yapılarak kesin karara bağlanır",
      "E": "Temyiz incelemesinde Danıştay idarenin takdir yetkisini kullanarak uyuşmazlığa konu yeni işlemi kendisi tesis eder"
    },
    "correctAnswer": "A",
    "explanation": "Kanun yararına bozma, hukuka aykırılığı giderici içtihat işlevi görür; daha önce kesinleşen kararın taraflar bakımından sonuçlarını kaldırmaz.",
    "source": {
      "kind": "generated",
      "styleRef": "2026 SMMM beş seçenekli test",
      "legislationRef": "2577 sayılı İYUK m.51/2"
    },
    "tags": [
      "Demo Soru",
      "2026 Formatı",
      "Konu Havuzu",
      "Süreler ve Kanun Yolları"
    ],
    "difficulty": "hard",
    "updatedAt": "2026-07-16T00:00:00Z",
    "examPeriod": "2026 test sistemine uyumlu özgün soru",
    "legislationVersion": "2577 sayılı İYUK (16.07.2026)",
    "sourceUpdatedAt": "2026-07-16T00:00:00Z",
    "isPremium": false,
    "isActive": true
  },
  {
    "id": "kh-iy-sure-0052",
    "lessonId": "idari_yargilama_hukuku",
    "topicId": "idari_yargida_sureler_kanun_yollari",
    "question": "Kanun yararına bozmanın kesinleşmiş merci kararına etkisi hangisidir?",
    "choices": {
      "B": "Kesinleşmiş kararın hukuki sonuçlarını kaldırmaz",
      "A": "Temyiz yalnız tarafların sözlü beyanıyla yapılır; dilekçe ve kanuni başvuru süresi aranmaz",
      "C": "Yargılamanın yenilenmesi kanunda sayılan sebeplere bağlı değildir ve kesinleşen her karar için süre sınırı olmadan istenebilir",
      "D": "İstinaf başvurusu doğrudan Danıştay Genel Kurulunca ilk derece incelemesi yapılarak kesin karara bağlanır",
      "E": "Temyiz incelemesinde Danıştay idarenin takdir yetkisini kullanarak uyuşmazlığa konu yeni işlemi kendisi tesis eder"
    },
    "correctAnswer": "B",
    "explanation": "Kanun yararına bozma, hukuka aykırılığı giderici içtihat işlevi görür; daha önce kesinleşen kararın taraflar bakımından sonuçlarını kaldırmaz.",
    "source": {
      "kind": "generated",
      "styleRef": "2026 SMMM beş seçenekli test",
      "legislationRef": "2577 sayılı İYUK m.51/2"
    },
    "tags": [
      "Demo Soru",
      "2026 Formatı",
      "Konu Havuzu",
      "Süreler ve Kanun Yolları"
    ],
    "difficulty": "hard",
    "updatedAt": "2026-07-16T00:00:00Z",
    "examPeriod": "2026 test sistemine uyumlu özgün soru",
    "legislationVersion": "2577 sayılı İYUK (16.07.2026)",
    "sourceUpdatedAt": "2026-07-16T00:00:00Z",
    "isPremium": false,
    "isActive": true
  },
  {
    "id": "kh-iy-sure-0053",
    "lessonId": "idari_yargilama_hukuku",
    "topicId": "idari_yargida_sureler_kanun_yollari",
    "question": "Dava açma süreleri bakımından hangileri doğrudur?\n\nI. İdare mahkemesinde genel süre altmış gündür\n\nII. Vergi mahkemesinde genel süre otuz gündür\n\nIII. Özel kanun farklı süre öngörebilir",
    "choices": {
      "D": "I, II ve III",
      "A": "I ve II",
      "B": "I ve III",
      "C": "II ve III",
      "E": "Yalnız I"
    },
    "correctAnswer": "D",
    "explanation": "İYUK m.7'deki altmış ve otuz günlük süreler, özel kanunda ayrı süre gösterilmeyen hâllerde uygulanır.",
    "source": {
      "kind": "generated",
      "styleRef": "2026 SMMM beş seçenekli test",
      "legislationRef": "2577 sayılı İYUK m.7/1"
    },
    "tags": [
      "Demo Soru",
      "2026 Formatı",
      "Konu Havuzu",
      "Süreler ve Kanun Yolları"
    ],
    "difficulty": "hard",
    "updatedAt": "2026-07-16T00:00:00Z",
    "examPeriod": "2026 test sistemine uyumlu özgün soru",
    "legislationVersion": "2577 sayılı İYUK (16.07.2026)",
    "sourceUpdatedAt": "2026-07-16T00:00:00Z",
    "isPremium": false,
    "isActive": true
  },
  {
    "id": "kh-iy-sure-0054",
    "lessonId": "idari_yargilama_hukuku",
    "topicId": "idari_yargida_sureler_kanun_yollari",
    "question": "Süre hesabı bakımından hangileri doğrudur?\n\nI. Süre bildirimi izleyen gün başlar\n\nII. Tatil günleri süreye dâhildir\n\nIII. Son gün tatilse süre önceki gün sona erer",
    "choices": {
      "B": "I ve II",
      "A": "I, II ve III",
      "C": "I ve III",
      "D": "II ve III",
      "E": "Yalnız I"
    },
    "correctAnswer": "B",
    "explanation": "Süre izleyen gün başlar ve tatiller hesaba katılır; son gün tatilse izleyen çalışma gününe uzar.",
    "source": {
      "kind": "generated",
      "styleRef": "2026 SMMM beş seçenekli test",
      "legislationRef": "2577 sayılı İYUK m.8"
    },
    "tags": [
      "Demo Soru",
      "2026 Formatı",
      "Konu Havuzu",
      "Süreler ve Kanun Yolları"
    ],
    "difficulty": "hard",
    "updatedAt": "2026-07-16T00:00:00Z",
    "examPeriod": "2026 test sistemine uyumlu özgün soru",
    "legislationVersion": "2577 sayılı İYUK (16.07.2026)",
    "sourceUpdatedAt": "2026-07-16T00:00:00Z",
    "isPremium": false,
    "isActive": true
  },
  {
    "id": "kh-iy-sure-0055",
    "lessonId": "idari_yargilama_hukuku",
    "topicId": "idari_yargida_sureler_kanun_yollari",
    "question": "İYUK m.11 başvurusu bakımından hangileri doğrudur?\n\nI. Dava açma süresi içinde yapılır\n\nII. İşleyen dava süresini durdurur\n\nIII. Retten sonra başvurudan önce geçen süre hesaba katılmaz",
    "choices": {
      "A": "I ve II",
      "B": "I, II ve III",
      "C": "I ve III",
      "D": "II ve III",
      "E": "Yalnız I"
    },
    "correctAnswer": "A",
    "explanation": "Başvuru süresinde yapılır ve dava süresini durdurur; ret sonrası önce geçen süre hesaba katılır.",
    "source": {
      "kind": "generated",
      "styleRef": "2026 SMMM beş seçenekli test",
      "legislationRef": "2577 sayılı İYUK m.11"
    },
    "tags": [
      "Demo Soru",
      "2026 Formatı",
      "Konu Havuzu",
      "Süreler ve Kanun Yolları"
    ],
    "difficulty": "hard",
    "updatedAt": "2026-07-16T00:00:00Z",
    "examPeriod": "2026 test sistemine uyumlu özgün soru",
    "legislationVersion": "2577 sayılı İYUK (16.07.2026)",
    "sourceUpdatedAt": "2026-07-16T00:00:00Z",
    "isPremium": false,
    "isActive": true
  },
  {
    "id": "kh-iy-sure-0056",
    "lessonId": "idari_yargilama_hukuku",
    "topicId": "idari_yargida_sureler_kanun_yollari",
    "question": "Yürütmenin durdurulması bakımından hangileri doğrudur?\n\nI. Dava açılması kural olarak yürütmeyi durdurmaz\n\nII. Açık hukuka aykırılık ile telafisi güç zarar birlikte aranır\n\nIII. Kararda iki koşulun gerekçesi gösterilir",
    "choices": {
      "C": "I, II ve III",
      "A": "I ve II",
      "B": "I ve III",
      "D": "II ve III",
      "E": "Yalnız I"
    },
    "correctAnswer": "C",
    "explanation": "Üç ifade de yürütmenin durdurulmasına ilişkin genel sistemi doğru açıklar.",
    "source": {
      "kind": "generated",
      "styleRef": "2026 SMMM beş seçenekli test",
      "legislationRef": "2577 sayılı İYUK m.27"
    },
    "tags": [
      "Demo Soru",
      "2026 Formatı",
      "Konu Havuzu",
      "Süreler ve Kanun Yolları"
    ],
    "difficulty": "hard",
    "updatedAt": "2026-07-16T00:00:00Z",
    "examPeriod": "2026 test sistemine uyumlu özgün soru",
    "legislationVersion": "2577 sayılı İYUK (16.07.2026)",
    "sourceUpdatedAt": "2026-07-16T00:00:00Z",
    "isPremium": false,
    "isActive": true
  },
  {
    "id": "kh-iy-sure-0057",
    "lessonId": "idari_yargilama_hukuku",
    "topicId": "idari_yargida_sureler_kanun_yollari",
    "question": "Yürütmenin durdurulmasına itiraz bakımından hangileri doğrudur?\n\nI. Tebliği izleyen günden itibaren yedi günlük süre vardır\n\nII. İtiraz bir defaya mahsustur\n\nIII. İtiraz üzerine verilen karar yeniden aynı yolla sınırsız incelenir",
    "choices": {
      "D": "I ve II",
      "A": "I, II ve III",
      "B": "I ve III",
      "C": "II ve III",
      "E": "Yalnız I"
    },
    "correctAnswer": "D",
    "explanation": "İtiraz yedi gün içinde ve bir defa yapılabilir; itiraz üzerine verilen karar kesindir.",
    "source": {
      "kind": "generated",
      "styleRef": "2026 SMMM beş seçenekli test",
      "legislationRef": "2577 sayılı İYUK m.27/7"
    },
    "tags": [
      "Demo Soru",
      "2026 Formatı",
      "Konu Havuzu",
      "Süreler ve Kanun Yolları"
    ],
    "difficulty": "hard",
    "updatedAt": "2026-07-16T00:00:00Z",
    "examPeriod": "2026 test sistemine uyumlu özgün soru",
    "legislationVersion": "2577 sayılı İYUK (16.07.2026)",
    "sourceUpdatedAt": "2026-07-16T00:00:00Z",
    "isPremium": false,
    "isActive": true
  },
  {
    "id": "kh-iy-sure-0058",
    "lessonId": "idari_yargilama_hukuku",
    "topicId": "idari_yargida_sureler_kanun_yollari",
    "question": "Kanun yolları bakımından hangileri doğrudur?\n\nI. İstinafın genel süresi otuz gündür\n\nII. Temyizin genel süresi otuz gündür\n\nIII. Her istinaf kararı parasal sınıra bakılmaksızın temyize açıktır",
    "choices": {
      "B": "I ve II",
      "A": "I, II ve III",
      "C": "I ve III",
      "D": "II ve III",
      "E": "Yalnız I"
    },
    "correctAnswer": "B",
    "explanation": "İstinaf ve temyiz için genel süre otuz gündür; her bölge idare mahkemesi kararı temyize açık değildir.",
    "source": {
      "kind": "generated",
      "styleRef": "2026 SMMM beş seçenekli test",
      "legislationRef": "2577 sayılı İYUK m.45-46"
    },
    "tags": [
      "Demo Soru",
      "2026 Formatı",
      "Konu Havuzu",
      "Süreler ve Kanun Yolları"
    ],
    "difficulty": "hard",
    "updatedAt": "2026-07-16T00:00:00Z",
    "examPeriod": "2026 test sistemine uyumlu özgün soru",
    "legislationVersion": "2577 sayılı İYUK (16.07.2026)",
    "sourceUpdatedAt": "2026-07-16T00:00:00Z",
    "isPremium": false,
    "isActive": true
  },
  {
    "id": "kh-iy-sure-0059",
    "lessonId": "idari_yargilama_hukuku",
    "topicId": "idari_yargida_sureler_kanun_yollari",
    "question": "Temyiz incelemesi sonunda Danıştay hangilerini yapabilir?\n\nI. Hukuka uygun kararı onayabilir\n\nII. Etkili usul hatası varsa bozabilir\n\nIII. İdarenin yerine geçerek yeni idari işlem kurabilir",
    "choices": {
      "C": "I ve II",
      "A": "I, II ve III",
      "B": "I ve III",
      "D": "II ve III",
      "E": "Yalnız I"
    },
    "correctAnswer": "C",
    "explanation": "Danıştay hukuka uygun kararı onar, kanundaki bozma sebeplerinde bozar; idari işlem tesis etmez.",
    "source": {
      "kind": "generated",
      "styleRef": "2026 SMMM beş seçenekli test",
      "legislationRef": "2577 sayılı İYUK m.49"
    },
    "tags": [
      "Demo Soru",
      "2026 Formatı",
      "Konu Havuzu",
      "Süreler ve Kanun Yolları"
    ],
    "difficulty": "hard",
    "updatedAt": "2026-07-16T00:00:00Z",
    "examPeriod": "2026 test sistemine uyumlu özgün soru",
    "legislationVersion": "2577 sayılı İYUK (16.07.2026)",
    "sourceUpdatedAt": "2026-07-16T00:00:00Z",
    "isPremium": false,
    "isActive": true
  },
  {
    "id": "kh-iy-sure-0060",
    "lessonId": "idari_yargilama_hukuku",
    "topicId": "idari_yargida_sureler_kanun_yollari",
    "question": "Yargılamanın yenilenmesi bakımından hangileri doğrudur?\n\nI. Kanunda sayılan sebeplere dayanır\n\nII. Esas kararı vermiş mahkemece incelenir\n\nIII. Her memnuniyetsizlik tek başına yenileme sebebidir",
    "choices": {
      "B": "I ve II",
      "A": "I, II ve III",
      "C": "I ve III",
      "D": "II ve III",
      "E": "Yalnız I"
    },
    "correctAnswer": "B",
    "explanation": "Yargılamanın yenilenmesi olağanüstü ve sınırlı sebeplere bağlıdır; esas kararı veren mahkeme inceler.",
    "source": {
      "kind": "generated",
      "styleRef": "2026 SMMM beş seçenekli test",
      "legislationRef": "2577 sayılı İYUK m.53"
    },
    "tags": [
      "Demo Soru",
      "2026 Formatı",
      "Konu Havuzu",
      "Süreler ve Kanun Yolları"
    ],
    "difficulty": "hard",
    "updatedAt": "2026-07-16T00:00:00Z",
    "examPeriod": "2026 test sistemine uyumlu özgün soru",
    "legislationVersion": "2577 sayılı İYUK (16.07.2026)",
    "sourceUpdatedAt": "2026-07-16T00:00:00Z",
    "isPremium": false,
    "isActive": true
  }
]
